Workbook

Sheet Main scores
C1: Qwen2.5 | I1: Qwen3 | M1: GPT-4o-mini (no RAG)
C2: 3B | F2: 7B | I2: 4B | K2: 8B
B3: Copilot (GPT-4o-mini + RAG) | C3: Instruct | D3: Fine Tuned | E3: FT Simple Prompt | F3: Instruct | G3: Fine Tuned | H3: FT Simple Prompt | I3: Instruct | J3: Fine Tuned | K3: Instruct | L3: Fine Tuned
A4: RAGAS - Answer Correctness (GPT-4o-mini) | B4: =AVERAGE('Ragas - Answer Correctness (GPT'!D4:D45) -> 0.70747534 | C4: =AVERAGE('Ragas - Answer Correctness (GPT'!E4:E45) -> 0.45506543 | D4: =AVERAGE('Ragas - Answer Correctness (GPT'!F4:F45) -> 0.50221622 | E4: =AVERAGE('Ragas - Answer Correctness (GPT'!G4:G45) -> 0.46975804 | F4: =AVERAGE('Ragas - Answer Correctness (GPT'!H4:H45) -> 0.53343197 | G4: =AVERAGE('Ragas - Answer Correctness (GPT'!I4:I45) -> 0.48207709 | H4: =AVERAGE('Ragas - Answer Correctness (GPT'!J4:J45) -> 0.48656974 | M4: =AVERAGE('Ragas - Answer Correctness (GPT'!O4:O45) -> 0.5851107
A5: RAGAS - Answer Correctness (GPT-4) | B5: =AVERAGE(Sheet1!D5:D46) -> 0.77028349 | C5: =AVERAGE(Sheet1!E5:E46) -> 0.44366684 | D5: =AVERAGE(Sheet1!F5:F46) -> 0.53750118 | E5: =AVERAGE(Sheet1!G5:G46) -> 0.49730108 | F5: =AVERAGE(Sheet1!H5:H46) -> 0.50213987 | G5: =AVERAGE(Sheet1!I5:I46) -> 0.5000876 | H5: =AVERAGE(Sheet1!J5:J46) -> 0.49817454 | M5: =AVERAGE(Sheet1!O5:O46) -> 0.5637488
A6: RAGAS - Semantic Similarity (Ada 002) | B6: =AVERAGE('Semantic Similarity (Ada 002)'!D5:D46) -> 0.94855422 | C6: =AVERAGE('Semantic Similarity (Ada 002)'!E5:E46) -> 0.89497962 | D6: =AVERAGE('Semantic Similarity (Ada 002)'!F5:F46) -> 0.91045853 | E6: =AVERAGE('Semantic Similarity (Ada 002)'!G5:G46) -> 0.90970354 | F6: =AVERAGE('Semantic Similarity (Ada 002)'!H5:H46) -> 0.90372747 | G6: =AVERAGE('Semantic Similarity (Ada 002)'!I5:I46) -> 0.91020488 | H6: =AVERAGE('Semantic Similarity (Ada 002)'!J5:J46) -> 0.91402446 | M6: =AVERAGE('Semantic Similarity (Ada 002)'!O5:O46) -> 0.90035507

Sheet Sample Answers
E1: Qwen2.5 | K1: Qwen3 | O1: GPT-4o-mini
E2: 3B | H2: 7B | K2: 4B | M2: 8B
A3: # | B3: Question | C3: Ground truth | D3: Copilot (GPT-4o-mini + RAG) | E3: Instruct | F3: Fine Tuned | G3: FT Simple Prompt | H3: Instruct | I3: Fine Tuned | J3: FT Simple Prompt | K3: Instruct | L3: Fine Tuned | M3: Instruct | N3: Fine Tuned
A4: 1 | B4: How to deploy a webapp? | C4: To deploy a web application in Choreo, follow the steps below: 1. **Create a project**: On the organization home page, click **+ Create Project**. Enter a display name, unique name, and description for the project. Click **Create**. This creates the project and opens the project home page. 2. **Create a Web Application component**: On the project home page, click **Web Application** under **Create a Single Component**. Enter a unique name and a description for the web application. 3. **Connect to GitHub**: Go to the **GitHub** tab and click **Authorize with GitHub**. If you have not already connected your GitHub repository to Choreo, enter your GitHub credentials and select the repository. You can also paste the repository URL in the **Provide Repository URL** field to connect to it without requiring authorization. 4. **Enter the required information**: Enter the required information such as your GitHub account in the **Organization** field, repository name in the **Repository** field, and the branch name in the **Branch** field. 5. **Select Buildpack**: Select a build Buildpack (eg: NodeJS, React, Python,PHP, etc.) as the **Buildpack** and provide the necessary details (eg: Project Directory, Language Version, Port, etc.). 6. **Create the component**: Click **Create**. Choreo initializes the component with the sample implementation and opens the **Overview** page of the component. 7. **Build your web application**: In the left navigation menu, click **Build**.In the Builds pane, click **Build**. This opens the Commits pane, where you can see all the commits related to the component. Select the latest commit and click **Build**. This triggers the build process and displays the progress in the **Build Logs pane**. 8. **Deploy the web application**: In the left navigation menu, click **Deploy**. In the **Set Up** card, click **Configure and Deploy**. Click **Next** to move to the **Authentication Settings** pane. Keep the default settings and click **Deploy**. 9. **Verify the deployment**: To verify that you have successfully hosted the web application, click the **Web App URL** in the **Development** card. This takes you to the web application. | D4: To deploy a web application using Choreo, you need to create a Web Application component and connect it to a Git repository containing your web application's source code. Here’s a structured approach to do this: ### Steps to Deploy a Web Application 1. **Create a Web Application Component**: - On the project home page, click on **Web Application** under the **Create a Component** section. - Choose to **Authorize with GitHub** to connect Choreo to your GitHub account. If you haven’t connected your GitHub repository yet, you will need to enter your credentials and select the appropriate repository. Alternatively, you can use a public GitHub repository by pasting the repository URL in the provided field. 2. **Enter Repository Details**: - Fill in the following information: | **Field** | **Value** | |------------------------------|-----------------------------| | **GitHub Account** | Your account | | **GitHub Repository** | Your repository name | | **Branch** | main (or your target branch)| | **Component Directory** | The directory of your application (if applicable) | 3. **Select Buildpack and Specify Build Options**: - Choose the relevant buildpack based on your web application framework (e.g., **React**, **Angular**, or **NodeJS** for server-side applications). - Provide the necessary build command, build path, and specify the Node.js version if required: | **Field** | **Description** | |------------------------------|----------------------------| | **Build Command** | Command to build your app (e.g., `npm run build`) | | **Build Path** | Output directory (e.g., `build`) | | **Node Version** | Specify the Node.js version (e.g., `18`) | 4. **Configure Application Settings**: - Enter a unique name and description for your web application component. 5. **Create the Component**: - Click **Create**. Choreo will initialize the component with the provided settings and open the **Overview** page of the component. 6. **Build and Deploy**: - Once the component is created, Choreo should automatically generate a build pipeline for your web application and deploy it. ### Additional Notes - If you are deploying a simple static website, you can use the **Static Websites** buildpack, which doesn't trigger a build process and serves the files directly from the specified path in your repository. - If you are using a Dockerfile for a containerized application, connect a repository containing the Dockerfile and follow the appropriate build steps. For more detailed instructions, you can refer to the following documents: - [Build and Deploy a Single-Page Web Application](https://wso2.com/choreo/docs/develop-components/develop-web-applications/build-and-deploy-a-single-page-web-application/#create-a-web-application) - [Deploy Your First Static Web Application](https://wso2.com/choreo/docs/quick-start-guides/deploy-your-first-static-web-application/#step-2-create-a-web-application-component) | E4: Deploying a web app on the Choreo platform typically involves several steps, but since I don't have direct access to the Choreo environment, I will guide you through the process assuming it's similar to deploying a web application in any environment. If you need more specifics about Choreo, consider looking into the documentation available there. ### Step-by-Step Guide to Deploy a Web App #### 1. Set Up Your Development Environment Make sure your local development environment is ready. You need Node.js and NPM (Node Package Manager) installed. You can install Node.js from [nodejs.org](https://nodejs.org/). Also, make sure you have Git for version control. ```sh # Install Node.js (latest LTS release) # Open https://nodejs.org/en/ ``` #### 2. Create Your Web App You can use a text editor or IDE (Integrated Development Environment) to write your web application code. Let’s assume your web application is a simple Express.js application. Here are the steps to create one: ```js // app.js const express = require('express'); const app = express(); const PORT = process.env.PORT || 3000; app.get('/', (req, res) => { res.send('Welcome to my Web App! '); }); app.listen(PORT, () => { console.log(`App running on port ${PORT}`); }); ``` Install Express.js using npm: ```sh npm install express ``` Initialize a new Node.js project: ```sh npm init -y ``` #### 3. Commit Files Commit your changes to your Git repository: ```sh git init git add . git commit -m "Add my first web application" ``` #### 4. Push to a Version Control System If your organization has a centralized source control system, push the code to the repository: ```sh git push origin master ``` #### 5. Create an API Service (if needed) If your application needs to interact with a backend, you might be setting up an API service too. Create the necessary files, and then you can use Choreo’s API services to set this up. For instance, create an API endpoint like `users`: ```js // user.js const express = require('express'); const app = express(); app.post('/api/users', (req, res) => { const user = req.body; res.send({message: 'User created!', user}); }); app.listen(3001, () => { console.log(`User Service running on port 3001`); }); ``` Again, initialize a Node.js project, commit the changes, push to the repository, and set up your API in Choreo. #### 6. Connect Services and Consumers Using Choreo’s Dashboard and/or its CLI, connect your web app and API services. Ensure they are communicating securely with each other (using OAuth, JWT tokens, etc.). #### 7. Deploy to Choreo (Optional Step) To deploy your app to Choreo, you may want to create a choreo-app.json file if you’re using a custom solution or utilize their built-in support for automatic deployments: ```json { "deploy": { "type": "auto" } } ``` In Choreo Dashboard, go to **Projects**, create or select an existing project, and follow their deployment instructions or connect to your service. Please note, this example is a generic guide. Detailed instructions depend on the specific needs and configuration required by your web app and Choreo service integration. For further detailed steps and security configurations, please consult the Choreo documentation: . | F4: To deploy a web application on the Choreo platform, follow these steps: ### Prerequisites 1. Ensure you have the required permissions for your organization. Typically, the minimum required permissions are: **Organization Read**, **Project Read**, and **Project Write**. ### Steps to Deploy a Web Application in Choreo 1. **Create a Web Application Component**: If you already have an application connected to your Git repository, proceed to the next step. Otherwise, connect your GitHub repository to Choreo by following the [Choreo Connect GitHub Repositories](https://wso2.com/choreo/docs/develop-components/develop-web-applications/connect-github-repos-choreo/#connect-github-repos-to-choreo) guide. 2. In the left navigation menu of the Choreo Console, click **Deploy**. 3. Select your component from the list of components to view the **Deploy** page. 4. In the **Set Up** card on the **Deploy** page, ensure you have filled in the mandatory fields such as a display name, name, version, project, label, description, and build pack. 5. Click on **Deploy** to start the deployment process. The build configuration will appear once the deployment completes successfully. ### Additional Notes - Choreo automatically applies best practices like microservices architecture and follows a modular design principle. - After the initial deployment, you can update the source code, apply new configurations, or rebuild your container image when changes are made in the source code repositories linked to the respective components. For more detailed guidance, you can refer to the official documentation here: [Deploy Your First Web Application](https://wso2.com/choreo/docs/develop-components/deploy-your-first-web-application/#step-3-deploy-the-web-application). | G4: To deploy a web application in Choreo, follow these steps: 1. **Deploy an Application**: - In the Choreo Console left navigation menu, click on **Deploy**. - Select **Web Application** as the buildpack. - Enter your details for deployment, including the name and description. - Click **Configure & Deploy**. The readiness and liveness checks will be automatically configured based on the file type you selected (for example, it will check for a `index.html` file for Node.js applications). - Provide appropriate configurations depending on your application type and save them. 2. **Configure Endpoint Mapping**: - Optionally, configure an endpoint mapping if you want to customize the domain name for accessing your app. If not needed, proceed to the next step. 3. **Promote to Production**: - Click the **Production** card on the Deployment page. - Confirm that the environment label in your Docker image is set to production before proceeding. - Click **Promote** to finalize the promotion. After deploying, your web application will be accessible at its publicly routable URL. If you are using a custom domain, ensure the container name matches your CNAME alias. ### Additional Notes: - You can connect a database when promoting your web application if you have a service connected via buildpack-based microservices. - Be aware of Choreo's logging constraints; logs from your application may not be available after two days and API gateway logs from the past seven days are deleted daily. For further details and specific instructions related to configuring endpoints and promotions, you can refer to the following documentation links: - [Deploy a Single-Page Web Application](https://wso2.com/choreo/docs/develop-components/deploy-a-single-page-web-application/#step-1-deploy-the-web-application) - [Configure Endpoints](https://wso2.com/choreo/docs/develop-components/configure-endpoints/) - [Promote Your Web Application](https://wso2.com/choreo/docs/develop-components/deploy-an-application/) | H4: Deploying a web application on Choreo typically involves integrating it as a service or API within the Choreo environment. However, please note that Choreo primarily focuses on API integration, webhooks, and service management rather than hosting full web applications. If you want to host and manage a web application alongside your APIs in Choreo, you might need to use additional resources or configure your web app to be triggered by events managed within Choreo. Here's how you can deploy and manage a web app or service in Choreo: ### 1. Create a New Web App Service - **Log in to Choreo**: - Open your browser and navigate to the Choreo console URL. - Log in with your credentials. - **Create a New Service**: - In the left sidebar, click on `Services`. - Click on `Add` and select `Web App`. - **Configure Your Service**: - Fill in the required details such as `Name`, `Description`, and `Endpoint URL` (URL of your web app). - Specify the authentication method if needed (e.g., Basic Auth, OAuth). - Configure any necessary settings such as SSL, CORS, and others. ### 2. Integrate with APIs/Webhooks (Optional) - **Create an API**: - Navigate to the `APIs` section. - Click on `Create API` and fill in the required details. - Configure the API endpoints to interact with your web app. - **Integrate with Webhooks**: - Navigate to the `Webhooks` section. - Create a new webhook to trigger events (like HTTP requests) when specific conditions are met, which can then interact with your web app via its endpoint. ### 3. Manage Access Control (Authentication) - **Secure Access**: - Set up authentication and authorization for both the web app and any integrated APIs or webhooks. - You can use various authentication methods supported by Choreo, such as OAuth 2.0, Basic Auth, etc. ### 4. Test and Deploy - **Test the Web App Service**: - Use the `Tests` tab in the service details page to simulate interactions with your web app. - Ensure that the endpoints and interactions are working as expected. - **Deploy**: - Once everything is tested and configured, your web app is considered deployed in the context of Choreo. It can now be accessed and interacted with through the defined endpoints. ### Additional Considerations - **Monitoring and Observability**: - Utilize the logging and monitoring features in Choreo to track the performance and health of your web app interactions. - **Scaling and Performance**: - Configure scaling policies and performance settings if necessary to handle traffic. For more detailed steps and options, please refer to the official Choreo documentation: - [Choreo Services Documentation](https://wso2.com/library/docs/developer/products/choreo/services/) - [Choreo Webhooks Documentation](https://wso2.com/library/docs/developer/products/choreo/webhooks/) - [Choreo API Management Documentation](https://wso2.com/library/docs/developer/products/choreo/api-management/) If you need further assistance with specific configurations or advanced setups, feel free to ask! | I4: To deploy a web application using Choreo, you can follow these steps: ### Step 1: Create a New Project 1. In the Choreo Console, click on **Create**. 2. Choose the **Web Application** card. 3. Select your preferred programming language (such as Go, Java, Node.js, Python, etc.). 4. Provide a name, description, and other project details to complete the creation of your web application project. ### Step 2: Build the Web Application - Choreo automatically builds the source code you provide via a Dockerfile. It follows best practices for secure container building and provides enhanced security features for container creation. - Ensure your web application can be deployed to a specified URL, which will be part of the configuration required during deployment. ### Step 3: Deploy the Web Application - To deploy your web application, go to the **Deploy** section in the Choreo Console. - The deployment process may take some time. You will need to provide configurations for the application, such as domain and port. - After the deployment, verify the URL of your web application to ensure it's accessible. ### Additional Information - If your web application is in an HTTP service, you can invoke it directly through the URL. - For more detailed instructions, you can refer to the documentation on deploying and managing a web application: [Deploy and Manage a Web Application](https://wso2.com/choreo/docs/develop-components/deploy-and-manage-a-web-application). By following these steps, you should be able to successfully deploy your web application using Choreo. | J4: To deploy a web application in Choreo, follow these steps: 1. **Create a Web Application**: You start by creating a web application component. This involves selecting the type of web application you want to develop and configuring it within the Choreo console. For more details, refer to the documentation on creating a web application: [Develop a Web Application](https://wso2.com/choreo/docs/develop-components/develop-web-applications/). 2. **Build and Deploy the Web Application**: - Once your web application is created, navigate to the left menu and click on **Deploy**. - Under the **Build Area** section, click on **Build** to compile your application. - After a successful build, go to the **Deployment Area** section and click **Deploy**. This action will initiate the deployment of your application into the development environment. 3. **View Your Application**: After a successful deployment, you can access your application via the URL provided during the deployment process. 4. **(Optional) Promote the Web Application**: - If you wish to move your application to production, you can promote it. Click on **Promote** under the **Deployment Area** section, then select **Confirm & Promote** when prompted. - Review the configurations and click **Execute** to finalize the promotion to production. For further details, you can refer to the complete documentation on deploying a web application here: [Deploy a Web Application](https://wso2.com/choreo/docs/tutorials/develop-a-single-page-web-application/#step-5-deploy-and-test-the-web-application). | O4: To deploy a web application in Choreo, follow these steps: 1. **Log in to Choreo**: - Go to the Choreo dashboard and log in with your credentials. 2. **Create a New Web Application**: - Click on the **"Create"** button. - Select **"Web Application"** from the options. 3. **Configure Your Web Application**: - Provide a name and description for your web application. - Choose the appropriate runtime environment (e.g., Node.js, Java, etc.). - Set up any necessary configurations, such as environment variables. 4. **Develop Your Application**: - Use the integrated code editor to write your application code. - You can also upload files or connect to a version control system (like Git) to pull your code. 5. **Set Up Dependencies**: - If your application requires external libraries or dependencies, specify them in the configuration settings. 6. **Test Your Application**: - Use the built-in testing tools to ensure your application is functioning as expected. 7. **Deploy the Application**: - Once you are satisfied with your application, click on the **"Deploy"** button. - Choose the deployment environment (e.g., development, production). 8. **Monitor the Deployment**: - After deployment, you can monitor the application’s performance and logs through the Choreo dashboard. 9. **Access Your Web Application**: - Once deployed, you will receive a URL to access your web application. For more detailed instructions and specific configurations, refer to the official Choreo documentation on [Deploying Web Applications](https://choreo.dev/docs/deploying-web-apps).
A5: 5 | B5: How can I test my service? | C5: To test your service in **Choreo**, you can use the integrated **OpenAPI Console** within the **Choreo Console UI**. Here are the detailed steps to perform the test: **Steps to Test the Service in Choreo Console** 1. **Navigate to the Test Console**: - In the **Choreo Console** left navigation menu, click **Test** and then click **Console**. 2. **Select the Environment**: - In the **OpenAPI Console** that opens, select **Development** from the environment drop-down list. 3. **Choose the Endpoint**: - In the **Endpoint** list, select the relevant **REST endpoint** for your service. 4. **Test the GET Method**: - Expand the **GET /** method (e.g., **GET /books**). - Click **Try it out**. - Click **Execute**. - Check the **Server Response** section to see the response from the server. 5. **Test the POST Method**: - Expand the **POST /** method (e.g., **POST /books**). - Click **Try it out**. - Update the **request body** with the necessary parameters. For example: ``` { ""author"": ""Your Author"", ""status"": ""to_read"", ""title"": ""Your Title"" } ``` - Click **Execute**. - Check the **Server Response** section. On successful invocation, you should receive a **201 HTTP status code**. 6. **Additional Methods**: - Similarly, you can expand and test other methods (e.g., **PUT**, **DELETE**) available for your service by following the **Try it out** and **Execute** steps. | D5: To test a service in Choreo, you can follow these steps within the Choreo Console: 1. **Access the Test Console**: - In the left navigation menu, click on **Test** and then select **Console**. 2. **Select the Environment**: - In the OpenAPI Console, choose **Development** from the environment drop-down menu. 3. **Choose the Endpoint**: - From the **Endpoint** list, select your service's REST endpoint (for example, a Books REST Endpoint). 4. **Test a Method**: - Expand the desired method you want to test, such as **GET /books**, and click on **Try it out**. 5. **Execute the Test**: - Click on **Execute** to send the request. 6. **Check the Response**: - Look at the **Server Response** section to see the results of your test. You can also explore other methods in the OpenAPI Console, such as **POST** or **DELETE**, depending on the functionality of your service. For more detailed instructions, you can refer to the documentation [here](https://wso2.com/choreo/docs/quick-start-guides/deploy-your-first-service/#step-4-test-the-service). | E5: Testing your service in Choreo is essential to ensure it works as expected. Here’s a step-by-step guide on how to do this: ### Step 1: Test in the Choreo Dashboard 1. **Log into Your Choreo Dashboard**: Access your Choreo account and go to the Dashboard where you manage your services. 2. **Test the Service Locally**: Choreo has tools for testing your service locally before deploying it. Use these tools for small-scale tests. ### Step 2: Use External Consumers (Simulated Calls) To test how your service behaves when it's integrated with external consumers, use Choreo’s built-in External Consumers feature. 1. **Navigate to External Consumers**: - Go to the Choreo Dashboard, then find "External Consumers" in the navigation menu. - This section allows you to create, view, update, and delete external consumer calls. 2. **Create a New External Consumer Call**: - Click on the "New External Consumer" button to start. - Configure the details of the external consumer call, including the service endpoint URL. 3. **Invoke and Test**: - After configuring the external consumer, you can invoke it. - See the response from the external consumer call directly within Choreo. ### Step 3: Deploy Your Service 1. **Deploy to Cloud**: - Ensure that your service deployment complies with Choreo’s best practices. - Review any necessary settings in Choreo for cloud deployment. 2. **Monitor Your Service**: - After deployment, use the Monitoring tool in Choreo to keep track of service performance and health. ### Step 4: Test Integration (Optional but Recommended) If your service needs to be integrated with another application, perform tests there as well: 1. **Integrate External System**: - Integrate your Choreo service with an external application. - Follow the steps for integration as described in Choreo’s documentation. 2. **Verify Communication**: - Ensure messages or data flow between the two systems as expected. For more detailed guidance and specific configurations, you may want to consult Choreo’s documentation pages: - [External Consumers in Choreo](https://docs.choreo.wso2.com/en/latest/administering/ext_consumers/) - [Deploying to Choreo Cloud](https://docs.choreo.wso2.com/en/latest/deploy-and-manage/services/deployments/) Feel free to explore more resources and support if you encounter any difficulties! | F5: To test your service in Choreo, you can use both the **Choreo DevOps** and **Test Cloud** environments. Below are the steps to deploy and test your service using these environments: ### Testing Your Service in Choreo DevOps Environment 1. **Deploy the Service**: Follow the steps to deploy your service to the Choreo DevOps environment. - Connect your GitHub repository, either through the UI or API. - Fill in the necessary details like display name, description, labels, color theme, etc. - Ensure that your service builds and deploys successfully. - Access your component in the **Project** section and click on **Test**. ![Test component](https://wso2.com/choreo/docs/assets/img/choreo-samples/test-component.png) 2. **Invoke the API**: In the **Test Configurations** pane, configure the endpoint as needed (e.g., production credentials for secure testing). You can specify parameters, headers, or JSON payloads to interact with the API. ![Configure endpoint](https://wso2.com/choreo/docs/assets/img/choreo-samples/configure-endpoint.png) 3. **Execute Tests**: Click **Run All** to execute tests against all endpoints. Alternatively, select an endpoint to run specific tests. 4. **View Test Results**: If any failures occur, they will be marked in red, providing feedback on how to troubleshoot. The results will list the tests performed along with their statuses. 5. **Log Level Tuning**: Adjust the log level in the **Logging & Monitoring** tab if the service generates more logs than expected. This prevents flooding the output with unnecessary log information during testing. ### Testing Your Service in Test Cloud Environment In addition to the Choreo DevOps environment, you can also test your components in the Test Cloud environment for further validation. #### Steps to Deploy Your Component in Test Cloud: 1. Sign in to the Choreo console. 2. From the top navigation menu, click **Organization**, select your organization. 3. Go to the left navigation menu and select **Components** then choose your component to view its card. 4. Under the **Create Version** card, click **Deploy**. 5. In the **Set Up** card, provide the necessary configuration details and deploy your component to the Test Cloud environment. For detailed guidance, refer to the documentation on [Testing Services](https://wso2.com/choreo/docs/testing/test-services/#test-the-service-in-the-choreo-cloud-data-plane). ### Additional Tips - Ensure that your service has appropriate permissions configured, especially if it interacts with other services. This involves assigning scopes during deployment. For a comprehensive understanding, please refer to the documentation here: [Test Components Manually](https://wso2.com/choreo/docs/testing/test-components-manually/#test-your-service). | G5: To test your service in Choreo, you have two primary options: **Testing the Service UI** and **Testing from the Console**. Let’s explore each option in detail. ### 1. Testing the Service UI When testing services using the Choreo console, you will primarily focus on visualizing service details through the Service page. The key activities involve: - Monitoring service requests and responses through the Request/Response pane. - Observing operational data like CPU and memory usage displayed on the Overview page. - Evaluating the logs and health status shown in the Logs section. - Analyzing service-level metrics found in the Diagnostics tab, including latency. - Checking for warning signs such as errors in the request/response pane and significant drops in the status of your service. Additionally, if you need to troubleshoot issues, you can use the Diagnostic view on the Service page to check for failed or errored operations. ### 2. Testing from the Console The Console also allows for testing the service by creating a connection with it using a connection cookie. You would specify the parameters and invoke a method, which can include passing a payload. This method provides both synchronous and asynchronous calls for service invocation. Here’s how to create a connection: - Click on the project under the **Overview** section in the left navigation menu. - Choose the component for which you want to create a connection, then navigate to **Test** > **Connection**. - Define your service details, which include the required parameters, optional parameters, and service endpoint details. - Click **Create** after filling in the details. ### Additional Tips for Effective Service Testing - Ensure that your service is deployed and ready for testing. - Make sure you have defined connections in the desired environment for testing purposes. - Test different parameters and payloads to evaluate the behavior of your service under various conditions. For more detailed instructions, you can refer to the following documentation links: - [Testing Services](https://wso2.com/choreo/docs/testing/test-services-with-choreo-test-runner/#testing-the-service-ui) - [Test Service Endpoints - Build, Deploy, and Test a Service in Choreo](https://wso2.com/choreo/docs/testing/test-service-endpoints/#test-the-service-while-it-is-running-in-choreo) These resources will help you effectively test and debug your services within the Choreo ecosystem. | H5: To test your service in Choreo, follow these steps: 1. **Deploy Your Service**: - Ensure your service is deployed in Choreo. This typically involves creating a service that exposes endpoints for various operations like GET, POST, etc. 2. **Create an API**: - Go to the Services tab in Choreo and select the service you want to test. - Click on the "Add API" button to create an API from the service. - Follow the prompts to configure the API. 3. **Configure API Endpoints**: - Map the service operations to API endpoints. This involves setting up the request and response mappings for each operation. - Test individual operations to ensure they work as expected. 4. **Set Up Webhooks** (Optional but useful for real-time testing): - If you need to trigger actions on other systems when a particular event occurs in your service, set up webhooks. - Configure webhooks to call back external systems with events or data. 5. **Test Using Postman or cURL**: - Use tools like Postman or execute cURL commands to send HTTP requests to your API endpoints. - For example, if your API has a `GET` endpoint to fetch data, use the following command in your terminal: ```bash curl -X GET "https://api.example.com/data" ``` - Alternatively, you can use Postman to construct and send requests. 6. **Use the Built-in Tester**: - Navigate to the "Test" tab of the API you created. - Choose the operation you want to test. - Fill in any required fields and click the "Test" button. - Check the console output for any errors and verify the response. 7. **Monitor with Observability Tools**: - Enable logging and observability features in your service. - Monitor logs and metrics to check if the service behaves as expected under load and different conditions. 8. **Perform Security Testing**: - Verify that your API security settings are correctly configured. - Test with both valid and invalid credentials if applicable. - Check rate limiting, throttling, and authentication mechanisms. 9. **Load Testing**: - Once satisfied with single-user testing, perform load testing to see how the service handles multiple concurrent requests. - Tools like JMeter can be used to simulate high traffic scenarios. For detailed guidance, refer to the official Choreo documentation on: - [Creating and Configuring APIs](https://wso2.com/choreo/apis/) - [Testing APIs](https://wso2.com/choreo/api-testing/) - [Security Testing](https://wso2.com/choreo/api-security/) If you run into specific issues, make sure to provide error messages or describe the problem in detail so I can offer more targeted advice. | I5: To effectively test a service in Choreo, you can follow several approaches depending on your specific requirements and the nature of your service: ### 1. **Manual Testing** - This involves invoking your component manually from the [Component Listing](https://devportal.choreo.dev/choreo/applications/{application-id}/components) page to verify its functionality. - Steps: 1. Navigate to the **Component Listing**. 2. Click on the desired component to open the **Overview** page. 3. Use the **Try it Out** option under the desired endpoint to test it directly. ### 2. **Integration Testing via the Choreo Console** - Utilize the Choreo Console to facilitate automated testing of service components. - This allows for testing the interactions between different services efficiently. - Note that integration tests can run on specific environments (Development, Staging, Production). ### 3. **Creating a Dedicated Test Component** - Develop a dedicated component solely for testing purposes within your Choreo project. - This approach helps isolate testing activities, ensuring they do not interfere with production systems. ### 4. **API Management Testing** - For API management, focus on validating endpoint functionalities, response statuses, latency, security features, and error conditions during testing. - Ensure that the API behavior meets expectations across different scenarios. ### 5. **Observability Insights** - Monitor your services using the observability insights in Choreo, which include logs, usage patterns, latency details, errors, and warnings. - This data can significantly enhance your testing process by providing real-time feedback. By combining these methods, you can thoroughly test your services in various scenarios and ensure their reliability. For more detailed steps and guidelines, please refer to the [Testing Services and Components Documentation](https://wso2.com/choreo/docs/testing/test-services-and-components/) in the Choreo documentation. | J5: To test a service in Choreo effectively, you can follow these steps and best practices: ### Step-by-Step Guide to Test Your Service in Choreo 1. **Access the Component**: - In the **Component Listing** pane, click on the component you want to test. 2. **Navigate to Testing**: - On the left navigation menu, click on **Test**. 3. **Choose Environment and Deployment Track**: - In the **Test** pane, select the appropriate environment from the drop-down list. - Select the relevant deployment track or version that you wish to test. 4. **Create a New Test Request**: - Click **+ Create** to start setting up your testing scenario. 5. **Set Up Test Parameters**: - Enter the required parameters based on your component type in the **Test Parameters** pane. - Click **Next**. 6. **Execute Your Tests**: - If applicable, you may provide values for additional test parameters in the respective sections. - Click **Execute**. This will trigger a series of tests: - **Schema Validation**: The request payload is validated against the OpenAPI specification. - **Security Context**: The context is injected to generate a call based on the specified protocol (REST or GraphQL). - **Request Handling**: Depending on the endpoint type, your application receives the request, and a response is generated and sent back through the test proxy. 7. **View Execution Results**: - After executing the test, you will see the execution results listed under the **Runbook** tab. Here, you can view response counts and failure rates. ### Best Practices for Testing Services - **Use Relative URLs**: For REST API endpoints, it's advisable to use relative URLs since they do not include a server host. - **Check API Definitions**: Ensure that your service is fully defined in Choreo, including parameters and body fields that must match the service’s implementation. - **Test Different Scenarios**: Run various test cases, including edge cases, to validate the service’s behavior across different scenarios - **Automated Testing**: If applicable, integrate automated testing into your workflow using tools like GitLab CI/CD for continuous integration. For more detailed information, you can refer to the documentation here: [Test a Service](https://wso2.com/choreo/docs/testing/test-a-service/) and [Testing Overview](https://wso2.com/choreo/docs/testing/test-services-and-integrations/). | O5: To test your service in Choreo, you can follow these steps: 1. **Access the Choreo Dashboard**: - Log in to your Choreo account and navigate to the dashboard. 2. **Select Your Service**: - From the dashboard, locate and select the service you want to test. 3. **Use the Test Feature**: - In the service details view, look for the "Test" option. This feature allows you to invoke your service directly from the dashboard. 4. **Configure Test Parameters**: - If your service requires input parameters, configure them in the test interface. You can specify the request body, headers, and any query parameters as needed. 5. **Execute the Test**: - Click on the "Test" button to send the request to your service. 6. **Review the Response**: - After executing the test, review the response returned by your service. This will include the status code, response body, and any headers. 7. **Debugging**: - If the response is not as expected, check the logs for any errors or issues. You can access logs through the observability features in Choreo. 8. **Iterate**: - Make any necessary adjustments to your service based on the test results and repeat the testing process as needed. For more detailed information, you can refer to the official Choreo documentation on [Testing Services](https://choreo.dev/docs/develop/testing-services).
A6: 18 | B6: What are the steps to secure an API in Choreo? | C6: To secure an API in Choreo, you can leverage various methods such as integrating with external Identity Providers (IdPs) like Microsoft Azure Active Directory (Azure AD) or Asgardeo, and implementing Role-Based Access Control (RBAC). Below are the general steps for each approach: Securing API Access with Microsoft Azure Active Directory (Azure AD) Assign Scopes to an API in Choreo: In the Component Listing pane, click on your API component. Navigate to Manage > Permissions. Click + Add Permission (Scope). Enter the permission value in the Permission List pane and click + Add New. Copy the fully qualified name of the scope for future reference. Attach the scope to a resource by selecting it from the Select Permissions list under the respective resource. Click Save and Deploy. Navigate to Manage > Lifecycle. Click Publish to publish your API to the Choreo Developer Portal. Create an API and Application in Azure AD: Follow Azure AD documentation to create an API and register an application. Configure the application to consume the Azure AD API. Enable External IdP Authentication in Choreo: Create an application in Choreo and configure it to use Azure AD as an external IdP. Invoke the API with Scopes: Use the assigned scopes to authenticate and authorize API invocations. For detailed steps, refer to the Secure API Access with Microsoft Azure Active Directory (Azure AD) documentation. Securing API Access with Asgardeo Assign Scopes to an API in Choreo: Similar to the Azure AD steps, assign scopes to your API in Choreo by navigating to Manage > Permissions and following the same steps to add permissions. Create an API and Application in Asgardeo: Follow Asgardeo documentation to create an API and register an application. Configure the application to consume the Asgardeo API. Enable External IdP Authentication in Choreo: Create an application in Choreo and configure it to use Asgardeo as an external IdP. Invoke the API with Scopes: Use the assigned scopes to authenticate and authorize API invocations. For detailed steps, refer to the Secure API Access with Asgardeo documentation." | D6: To secure an API in Choreo, you can follow these general steps, which will help you implement authentication and authorization effectively: ### Steps to Secure an API 1. **Assign Scopes to Your API**: Scopes are used to provide fine-grained access control to your API resources. - In the **Component Listing** pane, select the component you want to secure. - Navigate to **Manage** > **Permissions** in the left menu. - Click on **+ Add Permission (Scope)**. - In the **Permission List** pane, enter the permission value and click **+ Add New**. - Copy the fully qualified name of the scope for future reference. - Under the respective resource, select the scopes you want to attach and click **Save and Deploy**. - Finally, go to **Manage** > **Lifecycle** and click **Publish** to publish your API to the Choreo Developer Portal. 2. **Integrate an External Identity Provider (IdP)**: You can use providers like Microsoft Azure Active Directory (Azure AD) or Asgardeo for managing identity and access. - Create an API in your chosen IdP. - Create an application in the IdP and configure it to consume the API. - In Choreo, create an application and enable external IdP authentication. 3. **Implement Role-Based Access Control (RBAC)**: RBAC allows you to assign specific roles to users or groups, determining their permissions on API resources. - Define roles that correspond to different permission sets. - Assign roles to users or groups based on the required access levels to your API. 4. **Invoke the API with Scopes**: When invoking the API, ensure that the required scopes are included in the request to confirm the user's authorization. For detailed instructions on each step, you can refer to the following documents: - [Secure API Access with Microsoft Azure Active Directory (Azure AD)](https://wso2.com/choreo/docs/authentication-and-authorization/secure-api-access-with-azure-ad/) - [Secure API Access with Asgardeo](https://wso2.com/choreo/docs/authentication-and-authorization/secure-api-access-with-asgardeo/) - [Secure an API with Role-Based Access Control](https://wso2.com/choreo/docs/tutorials/secure-an-api-with-role-based-access-control/) These resources provide comprehensive guides on securing your API using various methods in Choreo. | E6: To secure an API in Choreo, you can use different security mechanisms depending on your needs and the complexity of your environment. Here’s a step-by-step guide to setting up basic OAuth 2.0 authorization flow for securing an API: ### Step 1: Configure Security First, enable security for your API. 1. Navigate to the **Integrations** section from your Choreo dashboard. 2. Find and click on the **APIs** or the API you want to secure. 3. In the sidebar menu, go to **Configure Security**. ### Step 2: Create a Key Manager Next, you need to define how client credentials and access tokens will be managed. 1. Click on **Key Manager** from the Configuration tab. 2. Under the Key Manager page, you'll find options for **Secret Key** and **Token Lifetime**. - Use secret keys when working with clients that are internal to your system. - Tokens have a predefined time limit to ensure short-lived access, enhancing security. ### Step 3: Set Up OAuth 2.0 Authorization Server OAuth 2.0 allows applications to securely access services. #### Substep 3a: Define Authentication and Token Endpoint 1. Under the key manager, go to **Settings** > **OAuth 2.0 Settings**. 2. Define the OAuth 2.0 authorization endpoint URL if needed. 3. Enter the necessary scopes for which you need authorization. #### Substep 3b: Grant Permissions to Consumers 1. Define your clients who need access to the API. 2. Specify permissions for each consumer using the **Client ID**. ### Step 4: Protect API Routes with Security Filters To ensure that only authenticated consumers can call your endpoints, configure security filters in Choreo. 1. From the Configuration page, switch to the **Security Filters** tab. 2. Enable the required filters based on your chosen security mechanism (e.g., API key, JWT, OAuth). #### Example: Using API Key Filter (as a simple example) 1. In Security Filters, add an API Key Filter by clicking the `Add Filter` button. 2. Specify the filter rules, like: - **Type**: Select **API Key** - **Method**: Choose the HTTP Method you are securing (e.g., POST, GET, etc.). - **Value**: This is where you can input API keys. - **Pattern**: If you want to validate against a token passed in the request header or query parameter. ### Step 5: Testing Your API Finally, don’t forget to test your API with sample scripts to confirm the security measures work as expected. 1. Go to the **Testing** tab after enabling it in Configuration settings. 2. Use tools provided to send requests and observe responses. ### Additional Notes - You might want to leverage additional security measures like implementing JWT (JSON Web Tokens) if you handle user sessions securely. - Regularly monitor logs for unusual activities related to your secured API to maintain safety and reliability. For detailed guidance, you may also refer to the official [Choreo documentation](https://docs.choreo.io). | F6: To secure an API in Choreo, you can utilize various methods that incorporate built-in security functions or implement JWT-based security tokens. Here’s a comprehensive guide on how to secure an API: ### 1. **Use Built-In Security Functions for API Level Authentication** - When creating an API component in Choreo, you have the option to enable security through the following mechanisms: - **Basic Authentication**: For this, set the `username` and `password` fields to define who can access the API. - **Bearer Token Authentication**: Generate a secret key and attach it to the endpoint URL to ensure secure communication. - To configure these settings: 1. In the **Component Listing** pane, click on the REST API you want to secure. 2. In the left navigation menu, click **Develop**, then select **Endpoints**. 3. Under **Security Overview**, click **Configure New Token** to set up appropriate roles and assign them to specific endpoints. ### 2. **Implement JWT-Based API Security** - To implement JSON Web Tokens (JWTs) for securing APIs: - Ensure you have an identity provider (IdP) set up, which can either be built-in or an external IdP. Choreo supports popular IdPs like Asgardeo, Azure AD, AWS Identity and Access Management, GitHub, and OpenID Connect applications. - In the Choreo Console, navigate to the project level under **Settings** > **Authentication Keys** and generate the necessary keys to test your JWT implementation. - After deployment, you can invoke the API securely via the generated endpoint URL. ### 3. **Deploying Your Application** - Once you have secured your API component, you need to deploy it to create the necessary keys for testing. This involves: - Creating an API in Developer Portal: 1. Click on the API component in the **Component Listing** pane. 2. Click **Manage**, then select **Endpoint** and copy the endpoint URL. - Invoking the API with the generated token to test its functionality. ### Important Considerations - Always ensure that the application is deployed before attempting to generate the test URL and invoking the API. - Properly handle secrets and tokens to maintain security throughout the API lifecycle. For further details on this topic, please refer to the official documentation: - [Secure API Access](https://wso2.com/choreo/docs/authentication-and-authorization/secure-api-access/) - [Secure an HTTP Service with Managed Identity](https://wso2.com/choreo/docs/authentication-and-authorization/secure-an-http-service-with-managed-idp/#step-4-generate-the-secrete-token-and-attach-it-to-the-http-service-endpoint) - [Configure Endpoints for Your API](https://wso2.com/choreo/docs/tutorials/expose-a-service-as-a-managed-api/#configure-endpoints-for-your-api) | G6: To secure APIs using Choreo, you can follow these main approaches: utilizing role-based access control and implementing API key-based security. Here’s a detailed overview of both methods: ### 1. Using Role-Based Access Control - **Principle of Least Privilege**: Each user in your organization is assigned one or more roles, and each role has specific permissions defined. This ensures that only users with appropriate roles have access to API endpoints. - **Assign Roles**: - You need to assign appropriate roles to users. The default roles in Choreo include: - API Publisher: Can create, publish, and manage APIs. - API Subscriber: Can consume APIs after subscribing. - Choreo provides out-of-the-box permissions for managing APIs, such as `LIST_API`, CREATE_API`, etc., which help in assigning roles effectively. - **Manage Users and Roles**: Ensure that the users associated with the roles have their login credentials and that their respective roles and permissions are properly configured. ![Configure roles and users](https://wso2.com/choreo/docs/assets/img/api-management/security/configure-roles-and-users.png) ![Manage subscriptions](https://wso2.com/choreo/docs/assets/img/api-management/security/manage-subscriptions.png) ### 2. Implementing API Key-Based Security - **API Keys**: - Each API in Choreo is configured with unique keys called API keys. These keys are essential for identifying and authorizing requests to the API. - API consumers can generate application keys programmatically and securely embed them into their clients to authenticate requests. Choreo also offers the option to generate API keys via the Developer Portal UI for testing purposes. - **Secure Application Keys**: - Choreo allows generating API keys in various languages, such as Go, Node.js, Java, PHP, Python, C#, or C++. It's important to ensure proper security measures when storing or transmitting these keys. - **API Key Lifecycle**: - API keys are valid until they reach their expiration date or are revoked manually through the Developer Portal UI. This helps maintain a robust security posture by limiting unauthorized access. For detailed guidance on securing APIs with Choreo, you can refer to the following documentation links: - [Secure API Consumption](https://wso2.com/choreo/docs/api-management/secure-api-consumption/) - [Secure APIs with Basic Authentication](https://wso2.com/choreo/docs/authentication-and-authorization/secure-apis-with-basic-authentication/) These steps will help you implement effective security measures for your APIs within Choreo. | H6: Securing APIs in Choreo involves several steps to ensure that your services and integrations are protected. Below are the key steps to secure an API in Choreo: 1. **Define Security Policies**: - Navigate to the API Manager in Choreo. - Define security policies such as OAuth 2.0, API keys, or custom policies to secure your API endpoints. 2. **Create and Configure API Keys**: - Generate API keys for external access. - Assign API keys to specific clients or users. 3. **Implement OAuth 2.0**: - Register your application with Choreo's OAuth provider. - Configure OAuth scopes and permissions. - Secure API endpoints using OAuth tokens. 4. **Configure CORS (Cross-Origin Resource Sharing)**: - Enable or disable Cross-Origin Resource Sharing based on your requirements. - Set allowed origins and headers. 5. **Enable SSL/TLS**: - Ensure that your API endpoints use HTTPS instead of HTTP to encrypt data in transit. 6. **Set Rate Limiting**: - Implement rate limits to prevent abuse and ensure fair usage. - Configure limits per user, IP address, or API key. 7. **Use Mutual TLS**: - Enable mutual TLS to secure client-server communication. - Provide certificates for both sides of the connection. 8. **Monitor and Logging**: - Enable detailed logging to monitor API usage. - Set up alerts for suspicious activities or API misuse. 9. **Security Auditing and Testing**: - Regularly audit your API security settings. - Perform security testing using tools like Postman or cURL to ensure proper security controls. 10. **Compliance Checks**: - Ensure your API security practices comply with relevant industry standards and regulations (e.g., GDPR, HIPAA). For more detailed steps and specific configurations, refer to the following sections in the official Choreo documentation: - [Defining Security Policies](https://wso2.com/library/tutorials/defining-security-policies/) - [API Keys Management](https://apim.docs.wso2.com/en/latest/administer/apikeys/) - [Enabling OAuth 2.0 in Choreo](https://apim.docs.wso2.com/en/latest/guide/quickstarts/securing-api-using-oauth2/) - [Configuring CORS](https://apim.docs.wso2.com/en/latest/administer/cors/) - [Setting Up Rate Limiting](https://apim.docs.wso2.com/en/latest/guide/quickstarts/limiting-traffic/) - [Configuring Mutual TLS](https://apim.docs.wso2.com/en/latest/guide/quickstarts/using-mutual-tls-certs/) - [Monitoring and Logging](https://apim.docs.wso2.com/en/latest/administer/monitor-and-log/) By following these steps and referring to the provided links, you can secure your APIs in Choreo effectively. | I6: To secure an API in Choreo, you can implement security measures at both the project level and component level. Here's how to do it: ### Secure an API at the Project Level 1. In the **Component Listing** pane, select the API Proxy you want to secure. 2. Navigate to **Manage** > **Endpoints**. 3. Click the edit icon corresponding to the desired endpoint. 4. Choose your security mechanism from the following options: - **Application Security**: Protects internal components using API proxies. It allows secure communication even without shared authentication among them, reducing the risk of exposure. - **OAuth2.0 Security**: Requires clients to obtain an access token before invoking the backend, ensuring secure API calls. 5. Optionally, you can set different audience values to restrict which applications can invoke the API. 6. Click **Update** and then deploy the proxy via the **Deploy** option to apply the changes. ### Secure an API at the Component Level 1. Select the API Proxy in the **Component Listing** pane. 2. Navigate to **Manage** > **Endpoints**. 3. Select the appropriate security scheme (similar options as above: Application Security or OAuth2.0 Security). 4. Click **Update**, then redeploy the API using the **Deploy** option. ### Additional Information Choreo provides various authentication methods such as API Key, OAuth2.0, and Google JSON Web Token (JWT). By implementing one of these, you can effectively secure your API. For detailed steps and more information, you can refer to the documentation here: [Secure APIs in Choreo](https://wso2.com/choreo/docs/authentication-and-authorization/secure-api-access/#step-1-secure-an-api-in-choreo). | J6: To secure APIs using role-based access control (RBAC) in Choreo, you can follow these steps: ### Step 1: Configure Role-Based Access Control 1. **Define Roles**: Define roles that specify permissions for various operations. Choreo has built-in roles such as: - **API Publisher** - **API Subscriber** - **API Admin** 2. **Attach Roles to Groups**: Attach these roles to specific groups within your organization. Each group can have multiple roles assigned. 3. **Assign Roles to Users**: Allow users to assign roles to their respective groups. Ensure users are aware of which actions they can perform based on their assigned roles. ### Step 2: Secure APIs There are three main methods to secure your APIs: #### Option 1: Secure API Access Using Asgardeo 1. In the **Components Listing** pane of Choreo Console, click **APIs** to view your APIs. 2. Select the desired API, then go to the **Manage** tab and choose **Subscription Policies**. 3. Choose **Asgardeo** as the identity provider and link it if necessary. 4. Follow the prompts to create a subscription policy for your API. **Prerequisites**: - Create a user store in Asgardeo. - Enable the `WSO2_IM_EXTERNAL_AUTHORITY` add-on for your project. - Ensure the application in Asgardeo is linked to the Choreo API and has appropriate permissions. #### Option 2: Implement API Level Security with Asgardeo 1. In Choreo, ensure you have created a project and added the API proxy component. 2. Navigate to the **Deploy** section for your component and generate a token via the **Test** tab. 3. Use this token to invoke the backend. ### Step 3: Enable and Manage Security Features 1. Navigate to your project in Choreo. 2. Select the **API Proxy** from the components list and go to the **Deploy** section. 3. Enable the necessary security features required for your API, such as API throttling. 4. Manage security keys in the **Credentials** tab of the API component. ### Additional Notes - Choreo enforces the principle of least privilege, meaning applications should only use the minimum necessary permissions granted by roles. - It is advisable to avoid granting permissions at the individual user level and to manage user access through their associated roles. By following these steps, you can effectively secure your APIs in Choreo using RBAC and other security measures. For more detailed information, you can refer to the documentation: - [Secure API access using Asgardeo](https://wso2.com/choreo/docs/authentication-and-authorization/secure-api-access-with-asgardeo/#step-3-to-create-an-api-in-choreo) - [Implement API-level Security with Asgardeo](https://wso2.com/choreo/docs/authentication-and-authorization/test-role-based-access-control-for-consumers-of-a-sevice/#step-1-enable-asgardeo-for-the-api-proxy-in-choreo) - [Manage Security Features](https://wso2.com/choreo/docs/api-management/manage-security-features/) | O6: To secure an API in Choreo, you can follow these steps: 1. **Create an API**: - Log in to your Choreo account. - Navigate to the "APIs" section and create a new API. 2. **Define Security Policies**: - In the API configuration, go to the "Security" tab. - Choose the appropriate security policy for your API. Choreo supports various authentication mechanisms such as OAuth2, API Key, and Basic Authentication. 3. **Configure OAuth2 (if applicable)**: - If you select OAuth2, configure the OAuth2 settings: - Set up the authorization server details. - Define the scopes required for accessing the API. 4. **Set Up API Key (if applicable)**: - If you choose API Key authentication, specify the API key requirements. - You can also define the key generation and validation process. 5. **Enable CORS (if needed)**: - If your API will be accessed from web applications, enable Cross-Origin Resource Sharing (CORS) in the API settings. 6. **Implement Rate Limiting (optional)**: - To protect your API from abuse, consider implementing rate limiting. This can be configured in the API settings. 7. **Test the Security Configuration**: - Use tools like Postman or curl to test the API endpoints with the configured security settings to ensure they are working as expected. 8. **Deploy the API**: - Once you have configured and tested the security settings, deploy the API to make it available for consumers. 9. **Monitor and Audit**: - Use Choreo's observability features to monitor API usage and audit access logs to ensure compliance and security. For more detailed information, you can refer to the official Choreo documentation on [API Security](https://choreo.dev/docs/apis/security).

Sheet Ragas - Answer Correctness (GPT
E1: Qwen2.5 | K1: Qwen3 | O1: GPT-4o-mini
E2: 3B | H2: 7B | K2: 4B | M2: 8B
A3: Question # | B3: Question | C3: Ground truth | D3: Copilot (GPT-4o-mini + RAG) | E3: Instruct | F3: Fine Tuned | G3: FT Simple Prompt | H3: Instruct | I3: Fine Tuned | J3: FT Simple Prompt | K3: Instruct | L3: Fine Tuned | M3: Instruct | N3: Fine Tuned
A4: 1 | B4: How to deploy a webapp? | C4: "To deploy a web application in Choreo, follow the steps below:\n\n1. **Create a project**: On the organization home page, click **+ Create Project**. Enter a display name, unique name, and description for the project. Click **Create**. This creates the project and opens the project home page. \n\n2. **Create a Web Application component**: On the project home page, click **Web Application** under **Create a Single Component**. Enter a unique name and a description for the web application. \n\n3. **Connect to GitHub**: Go to the **GitHub** tab and click **Authorize with GitHub**. If you have not already connected your GitHub repository to Choreo, enter your GitHub credentials and select the repository. You can also paste the repository URL in the **Provide Repository URL** field to connect to it without requiring authorization. \n\n4. **Enter the required information**: Enter the required information such as your GitHub account in the **Organization** field, repository name in the **Repository** field, and the branch name in the **Branch** field. \n\n5. **Select Buildpack**: Select a build Buildpack (eg: NodeJS, React, Python,PHP, etc.) as the **Buildpack** and provide the necessary details (eg: Project Directory, Language Version, Port, etc.). \n\n6. **Create the component**: Click **Create**. Choreo initializes the component with the sample implementation and opens the **Overview** page of the component.\n\n7. **Build your web application**: In the left navigation menu, click **Build**.In the Builds pane, click **Build**. This opens the Commits pane, where you can see all the commits related to the component. Select the latest commit and click **Build**. This triggers the build process and displays the progress in the **Build Logs pane**.\n\n8. **Deploy the web application**: In the left navigation menu, click **Deploy**. In the **Set Up** card, click **Configure and Deploy**. Click **Next** to move to the **Authentication Settings** pane. Keep the default settings and click **Deploy**. \n\n9. **Verify the deployment**: To verify that you have successfully hosted the web application, click the **Web App URL** in the **Development** card. This takes you to the web application." | D4: 0.56474119 | E4: 0.57106382 | F4: 0.4262119 | G4: 0.3631743 | H4: 0.6926953 | I4: 0.46526559 | J4: 0.71555427 | O4: 0.5573156
A5: 2 | B5: "How to resolve ""Module not found error"" during the deployment of a Python project?" | C5: "To resolve a **Module not found""** error during the deployment of a Python project in Choreo:\n\n1. **Verify Dependencies:**\n - Ensure all required Python modules are in `requirements.txt`\n - Example `requirements.txt`:\n ```plaintext\n flask\n requests\n numpy\n ```\n\n2. **Check File Paths:**\n - Verify that the modules and packages being imported in your Python code have the correct file paths\n\n3. **Rebuild the Component:**\n - Trigger a rebuild after updating `requirements.txt` or file paths. This will ensure that any changes made to the dependencies are included in the new build.\n\n4. **Inspect Logs:**\n - . If the error persists check build logs in Choreo Console UI for detailed error messages. The logs can provide more context on which module is not found and why. \n\n5. **Environment Configuration:**\n - Ensure correct setup of environment variables in Choreo. Sometimes environment variables might be needed for certain modules to work correctly.you can follow these steps:\n\n**Steps to Implement Custom Authentication:**\n\n1. **Add the Connection Configuration:**\n```window.configs = {\napiUrl: '<SERVICE_URL>'" | D5: 0.54867779 | E5: 0.57316999 | F5: 0.35876017 | G5: 0.74796175 | H5: 0.63736825 | I5: 0.57475838 | J5: 0.65960681 | O5: 0.83437842
A6: 3 | B6: How to add authentication to my service? | C6: "To add **authentication** to a service in **Choreo**, you can utilize **Choreo's managed authentication** or configure **custom authentication**. Here are the steps for integrating managed authentication and custom authentication:\n\n**Managed Authentication**\nManaged authentication is a feature provided by **Choreo** that simplifies the process of adding authentication and authorization to your web application. It supports web applications created with **React**, **Angular**, or **Vue.js** buildpacks.\n\n**Steps to Implement Managed Authentication:**\n\n1. **Implement Sign-in Functionality:**\n```<button onClick={() => { window.location.href = ""/auth/login"" }}>Login</button>```\nThis redirects users to the **login path** where **Choreo** handles the authentication process.\n\n2. **Obtain User Information Claims:**\n\n**Via Cookie:**\n```import Cookies from 'js-cookie';\nconst encodedUserInfo = Cookies.get('userinfo');\nconst userInfo = JSON.parse(atob(encodedUserInfo));\nCookies.remove('userinfo', { path: '/' });```\n\n**Via GET Endpoint:**\n```const response = await fetch('/auth/userinfo');```\n\n3. **Implement Sign-out Functionality:**\n```<button onClick={async () => { window.location.href = `/auth/logout?session_hint=${Cookies.get('session_hint')}`;}}>Logout</button>```\n\n4. **Invoke APIs:**\n```const response = await fetch('/choreo-apis/<api-suffix>');```\n\n**Custom Authentication**\nIf you prefer to handle authentication manually or use custom authentication mechanisms, you can follow these steps:\n\n**Steps to Implement Custom Authentication:**\n\n1. **Add the Connection Configuration:**\n```window.configs = {\napiUrl: '<SERVICE_URL>',\nconsumerKey: '<CONSUMER_KEY>',\nconsumerSecret: '<CONSUMER_SECRET>',\ntokenUrl: '<TOKEN_URL>',\n};```\n\n2. **Read the Configuration:**\n```const serviceURL = window?.configs?.apiUrl ? window.configs.apiUrl : ""/"";```\n\n3. **Acquire an OAuth 2.0 Access Token:**\n\n**Using a cURL Command:**\n```CONSUMER_KEY=""your_consumer_key""\nCONSUMER_SECRET=""your_consumer_secret""\nTOKEN_URL=""your_token_url""\nCLIENT_CREDENTIALS=$(echo -n ""$CLIENT_ID:$CLIENT_SECRET"" | base64)\ncurl -X POST $TOKEN_URL \n-H ""Content-Type: application/x-www-form-urlencoded"" \n-H ""Authorization: Basic $CLIENT_CREDENTIALS"" \n--data-urlencode ""grant_type=client_credentials""```\n\n4. **Invoke the Service:**\n```const response = await axios.get(serviceURL/{RESOURCE_PATH}, {\nheaders: {\n'Authorization': `Bearer ${accessToken}`\n}\n});```\n\nBy following these steps, you can successfully add **authentication** to your service in **Choreo** using either **managed authentication** or **custom authentication** methods." | D6: 0.55934262 | E6: 0.58262682 | F6: 0.53230351 | G6: 0.47141321 | H6: 0.43355567 | I6: 0.36731131 | J6: 0.46133877 | O6: 0.40845348
A7: 4 | B7: How to add a custom domain to my web app? | C7: "to add a custom domain to a web app in Choreo:\n\nPrerequisites:\n1. Ensure you have organization administrator privileges.\n2. Make sure your web app is deployed in the desired environment.\n\nSteps to Add a Custom Domain:\n1. **Sign in to the Choreo Console**.\n2. **Access Organization Settings**:\n * Click the **Organization** list in the Choreo Console header.\n * In the left navigation menu, click **Settings**.\n * Go to the **URL Settings** tab and then click the **Active Domains** tab.\n3. **Add the Custom Domain**:\n * Click **+ Add Domains**.\n * In the **Add a Custom Domain** pane, enter your domain name.\n * Select the environment where you want to apply the domain name.\n * Select the entity type as **Web App**.\n * Note the generated CNAME target value displayed and create a DNS record associating your domain name to the CNAME target value with your DNS provider.\n4. **Verify the Domain**:\n * Once the CNAME type DNS record is created, click **Verify**.\n5. **Configure TLS Certificates**:\n * On successful verification, click **Next**.\n * Select a TLS certificate provider. You can either import your own TLS certificates or allow Choreo to generate and manage the certificates using **Let's Encrypt**.\n6. **Save the Custom Domain**:\n * Click **Add** to save the custom domain.\n\nConfigure a Custom URL for Your Web App:\n1. **Request a Custom URL**:\n * Sign in to the Choreo Console.\n * In the **Component Listing** pane, click on your web app.\n * Click **Settings** in the left navigation menu.\n * Go to the **URL Settings** tab. If an active custom domain is available, the **Edit URL Mapping** icon in the corresponding **Action** column will be enabled.\n2. **Configure the URL**:\n * Click the **Edit URL Mapping** icon under the **Action** column for the desired environment.\n * Select the domain from the **Domain** drop-down list.\n * Click **Configure** to create the custom URL mapping. The custom URL request will be in **Pending** status until approved by an organization administrator.\n3. **Approval**:\n * The organization administrator needs to approve the custom URL request from the organization-level settings page under the **Pending URL Requests** tab.\n\nOnce the custom URL request is approved, the custom domain will be applied to your web app." | D7: 0.77918502 | E7: 0.34112693 | F7: 0.4381491 | G7: 0.40611852 | H7: 0.42356695 | I7: 0.66888358 | J7: 0.69224479 | O7: 0.55691398
A8: 5 | B8: How can I test my service? | C8: "To test your service in **Choreo**, you can use the integrated **OpenAPI Console** within the **Choreo Console UI**. Here are the detailed steps to perform the test:\n\n**Steps to Test the Service in Choreo Console**\n\n1. **Navigate to the Test Console**:\n - In the **Choreo Console** left navigation menu, click **Test** and then click **Console**.\n\n2. **Select the Environment**:\n - In the **OpenAPI Console** that opens, select **Development** from the environment drop-down list.\n\n3. **Choose the Endpoint**:\n - In the **Endpoint** list, select the relevant **REST endpoint** for your service.\n\n4. **Test the GET Method**:\n - Expand the **GET /** method (e.g., **GET /books**).\n - Click **Try it out**.\n - Click **Execute**.\n - Check the **Server Response** section to see the response from the server.\n\n5. **Test the POST Method**:\n - Expand the **POST /** method (e.g., **POST /books**).\n - Click **Try it out**.\n - Update the **request body** with the necessary parameters. For example:\n ```\n {\n ""author"": ""Your Author"",\n ""status"": ""to_read"",\n ""title"": ""Your Title""\n }\n ```\n - Click **Execute**.\n - Check the **Server Response** section. On successful invocation, you should receive a **201 HTTP status code**.\n\n6. **Additional Methods**:\n - Similarly, you can expand and test other methods (e.g., **PUT**, **DELETE**) available for your service by following the **Try it out** and **Execute** steps." | D8: 0.62592197 | E8: 0.22212626 | F8: 0.30835286 | G8: 0.70823447 | H8: 0.78375349 | I8: 0.4073839 | J8: 0.67838953 | O8: 0.97729073
A9: 6 | B9: How can I add environment variables to python webapp? | C9: "To set up environment variables in **Choreo**, follow these steps:\n\n**Steps to Apply Environment Variables**\n\n1. **Navigate to Your Component in Choreo Console**:\n - Go to the **Component Listing** pane and click on the component you want to configure.\n\n2. Access **Configurations & Secrets**:\n - In the left navigation menu, click **DevOps** and then click **Configs & Secrets**.\n\n3. **Create a New Environment Variable**:\n - Click **+ Create**.\n - In the **Create a Config or Secret** pane, select **Environment Variables**.\n\n4. **Mark as a Secret (Optional)**:\n - If you need the environment variable values to be secrets, select **Mark as a Secret**. Note that you will not be able to read these values after setting them.\n\n5. **Specify the Environment Variables**:\n - Enter the **Display Name** for your configuration or secret.\n - Under **Add Environment Variables**, specify the environment variables as **key-value pairs**.\n - Click **Add Item** to add more variables if needed.\n\n6. **Finalize Creation**:\n - Click **Create** to save your environment variables.\n\n**Additional Tips**\n\n- **Ballerina Configurables**: If you are dealing with Ballerina components, you can manage configurables separately. Configurables can be used instead of environment variables for file mounts in Ballerina components. \n\n**Security Note**\n\n- All configurations and secrets are stored in an encrypted secret vault managed by **WSO2** in the cloud data plane. If you are on a private data plane, they are stored in an **Azure key vault** or **AWS secret manager** attached to your data plane in your cloud environment." | D9: 0.90534994 | E9: 0.19929397 | F9: 0.39415423 | G9: 0.5235727 | H9: 0.66156785 | I9: 0.33814936 | J9: 0.6360666 | O9: 0.65656576
A10: 7 | B10: How to connect the React frontend to the backend? | C10: "1: Create and Deploy Your Backend Service\nFirst, ensure your backend service is deployed in Choreo. If you don't have a service yet, you can create one by following these steps:\n1. **Connect to Your Repository:**\n * On the project home page, click **Start** under **Create Multiple Components**.\n * Go to the **GitHub** tab and authorize Choreo to connect to your GitHub account.\n * Enter the repository URL and branch details.\n * Select and configure the backend service component.\n2. **Build and Deploy the Service:**\n * Click the service component listed under **Component Listing** on the project home page.\n * In the left navigation menu, click **Build** and then **Build Latest**.\n * Once the build is complete, proceed to deploy the service.\n\nStep 2: Create a React Frontend Application in Choreo\nNext, create a web application component for your React frontend:\n1. **Create the Web Application Component:**\n * In the Choreo Console header, select your project.\n * Click **+ Create** under **Component Listing**.\n * Select **Web Application** and fill in the necessary details (display name, unique name, description).\n * Authorize with GitHub to connect your repository.\n * Enter your GitHub account, repository, and branch details.\n * Select **React** as the buildpack.\n * Enter the build configuration details (`Project Directory`, `Build Command`, `Build Path`, `Node Version`).\n2. **Build the Web Application Component:**\n * In the left navigation menu, click **Build** and then **Build Latest**.\n\nStep 3: Connect the Web Application to the Backend Service\nTo establish a connection between your React frontend and the backend service:\n1. **Create a Connection:**\n * In the left navigation menu, click **Dependencies** and then **Connections**.\n * Click **+ Create** and select your backend service.\n * Provide a name and description for the connection and click **Create**.\n * Copy the service URL displayed for the Development environment.\n2. **Configure the Web Application:**\n * In the left navigation menu, click **Deploy** and then **Configure and Deploy**.\n * In the `config.js` file mount, replace `<Service URL>` with the copied service URL:\n ```javascript\n window.configs = {\n apiUrl: '<Service URL>',\n };\n ```\n * Ensure managed authentication is enabled and configure authentication settings (Post Login Path, Post Logout Path, Error Path).\n3. **Deploy the Web Application:**\n * Click **Deploy** in the **Authentication** pane.\n * Once deployed, copy the **Web App URL**.\n\nStep 4: Access and Test Your Application\n* Navigate to the web app URL to verify that your React frontend is successfully connected to the backend service." | D10: 0.44224883 | E10: 0.39853913 | F10: 0.53693657 | G10: 0.55640841 | H10: 0.36368641 | I10: 0.42883007 | J10: 0.40422513 | O10: 0.46933792
A11: 8 | B11: How can I deploy my backend and then connect it to the frontend deployed in github pages? | C11: "To deploy a backend service on Choreo and connect it to a frontend hosted on GitHub Pages, follow these steps:\n\nStep 1: Deploy the Backend Service on Choreo\n1. Create a Project in Choreo:\n * Go to the Choreo Console and sign in.\n * On the organization home page, click **+ Create Project**.\n * Enter a display name, unique name, and description for the project.\n * Click **Create** to create the project and open the project home page.\n\n2. Connect Your GitHub Repository and Configure the Service:\n * On the project home page, click **Start** under **Create Multiple Components**.\n * Go to the **GitHub** tab.\n * Click **Authorize with GitHub** to allow Choreo to connect to your GitHub account.\n * Enter the GitHub account details, repository, and branch.\n * In the **Add Component Directories** pane, click the + icon corresponding to your backend service directory.\n * Configure the service component by specifying details such as Component Display Name, Component Name, Path, Component Type, Buildpack, and Language Version.\n * Click **Save** and then **Finish** to initialize the service.\n\n3. Build and deploy the service\n 3.1: Build\n * On the project home page, click the service component you created. This takes you to the component overview page.\n * In the left navigation, click **Build**.\n * Click **Build Latest**. The build process may take a while, and you can track the progress via the logs in the Build Details pane.\n * Once the build process is complete, the build status changes to Success.\n\n 3.2: Deploy\n * In the left navigation menu, click **Deploy**.\n * On the **Set Up** card, click **Configure & Deploy**.\n * In the **Environment Configurations** pane, click **Next**.\n * In the **File Mount** pane, click **Next**.\n * Review the **Endpoint Details** and click **Deploy**. In the Endpoint Details pane that opens, ensure that the Network Visibility is set to Public. This setting securely exposes the endpoint for external consumption.\n * The deployment process may take some time, and you can track the progress by observing the logs.\n * Once the deployment is complete, the build status changes to Active on the Development environment card.\n\n Ensure that your backend service is configured to allow CORS (Cross-Origin Resource Sharing) requests from your frontend's domain (GitHub Pages). \n This is crucial for enabling communication between the two different domains.\n To do that follow these steps\n\n 3.3.: Enable CORS\n * From your Development card access endpoint details. \n * In the Endpoint Details pane Go to settings. \n * From the security tab in the settings you can allow CORS.\n\nTo connect your service to the frontend deployed outside choreo in this case github pages you need to get the public url for your service.\n\n4. Getting the Public URL:\n * Once the deployment is complete, navigate to the component overview page where you can find the service URL.\n * Copy the public URL of the service from the development environment card.\n\n5. Then you have to manually add this public URL as the API URL in your frontend code.\n Use this API URL in your frontend to make HTTP requests (e.g., GET, POST) to interact with your backend service." | D11: 0.72312157 | E11: 0.45004292 | F11: 0.38580039 | G11: 0.64118002 | H11: 0.26767344 | I11: 0.31217148 | J11: 0.39869876 | O11: 0.37076219
A12: 9 | B12: How can I implement testing for a full-stack application including automated testing for both frontend and backend components? | C12: "To implement automated testing for both frontend and backend components in a full-stack application using Choreo, follow these steps:\n\n**Backend Testing with Test Runner**\n\n**Create a Test Runner Component:**\n1. Go to the Choreo Console.\n2. **Click `+Create`** in the Component Listing section.\n3.Select **`Test Runner`.**\n4. Enter a unique name and description for the test runner component.\n5. Go to the `GitHub` tab and enter:\n - **GitHub Account**\n - **GitHub Repository**\n - **Branch**\n6. Select a buildpack based on the language of your choice.\n7. Enter the relevant values based on the selected buildpack.\n8. **Click `Create`.\n**Build and Deploy the Test Runner Component:**\n1. Navigate to `Build` on the left panel.\n2. **Click `Build`** and select the latest commit.\n3. Once the build completes, go to `Deploy`.\n4. **Click `Deploy`** to deploy the Test Runner component, or use `Configure and Deploy` for additional configurations.\n5. After deployment, go to `Execute` and select the environment.\n6. **Click `Run Now`** to trigger the test execution.\n7. Once execution is completed, click on a particular execution to view the test results.\n\n**Frontend Testing**\n\n**Access and Test Frontend Application:**\n1. Access the frontend application via its web URL.\n2. Perform manual testing by interacting with the application (e.g., adding items, checking user-specific data)." | D12: 0.41020742 | E12: 0.50092252 | F12: 0.42118544 | G12: 0.97967785 | H12: 0.46101058 | I12: 0.20334512 | J12: 0.29276247 | O12: 0.186414
A13: 10 | B13: "I'm getting ""procfile not found"" error for my python service. How do I resolve this?" | C13: "The error you're encountering is because Choreo requires a `Procfile` in your Python project's root directory. A `Procfile` is a configuration file used to declare the commands that are run by your application's containers. \n\nFor a Python project, your `Procfile` might look something like this:\n```\nweb: <command to start your application>\n``` \nFor example, if you're using Flask, your `Procfile` should look like this:\n```\nweb: flask run --host=0.0.0.0\n```\n\nPlease ensure that you have a `Procfile` in your project root directory and that it contains the appropriate command to start your application. You can refer more on this from the [Choreo documentation](https://wso2.com/choreo/docs/develop-components/deploy-an-application-with-buildpacks/#develop-a-component)." | D13: 0.57251179 | E13: 0.48344404 | F13: 0.21162041 | G13: 0.39772922 | H13: 0.63268276 | I13: 0.22714952 | J13: 0.68993475 | O13: 0.64972522
A14: 11 | B14: I'm getting .choreo/endpoints.yaml not found error. How do I resolve this? | C14: "The error message you're seeing, '.choreo/endpoints.yaml not found', indicates that the `endpoints.yaml` file is missing from your project's root directory in the `.choreo` folder. This file is required to define the endpoints for your service component. \n\nTo resolve this error, you need to create an `endpoints.yaml` file in the `.choreo` directory at the build context path and commit it to the source repository. The `endpoints.yaml` file should contain details about the endpoints that your service component will expose. Here is a sample `endpoints.yaml` file:\n\n```yaml\nversion: 0.1\nendpoints:\n- name: Your Service\n port: 9090\n type: REST\n networkVisibility: Project\n context: /your_service\n schemaFilePath: your_service_openapi.yaml\n```\n\nIn this file:\n\n- `name` is a unique name for the endpoint, which Choreo will use to generate the managed API.\n- `port` is the numeric port value that gets exposed via this endpoint.\n- `type` is the type of traffic this endpoint is accepting, such as `REST`, `GraphQL`, `gRPC`, `UDP`or `TCP`.\n- `networkVisibility` is the network level visibility of this endpoint, which defaults to `Public` if not specified. Accepted values are `Project`, `Organization`, or `Public`.\n- `context` is the context (base path) of the API that Choreo exposes via this endpoint. \n- `schemaFilePath` is the swagger definition file path. This field should be a relative path to the project path.\n\nPlease make sure to replace 'Your Service' and '/your_service' with the actual name and context of your service, and 'your_service_openapi.yaml' with the actual OpenAPI schema file.\n\nFor more detailed information about the `endpoints.yaml` file and its structure, you can refer to the following documentation" | D14: 0.98829978 | E14: 0.75239495 | F14: 0.71962209 | G14: 0.95231532 | H14: 0.32376275 | I14: 0.60414433 | J14: 0.21798168 | O14: 0.6397334
A15: 12 | B15: Tell me how I can configure a readiness probe? | C15: "To configure a readiness probe in Choreo, follow these steps:\n\n1. In the **Component Listing** pane, click on the component for which you want to configure readiness probes.\n2. In the left navigation menu, click **DevOps** and then click **Health Checks**.\n3. On the **Health Checks** page, click **+ Create**.\n4. Configure the readiness probe depending on your requirement.\n5. Click **Save**. \n\nYou can update or remove a probe at any time. After setting up the probe, you can ensure that the container works as expected by clicking **Runtime** under **DevOps** in the left navigation menu. On the **Runtime** page, check the details to confirm that the container works as expected. If the container does not start, check the **events and conditions** to see if any of the probes are causing the container to fail.\n\nReadiness probes run periodically throughout the lifecycle of a container. Unlike liveness probes, these probes do not restart the container if the probe fails. Instead, they stop the container from receiving network traffic. Be mindful when you configure readiness probes on a single-running replica. If the readiness probe fails, your application stops receiving traffic because there is only one active replica. The application may not recover unless the liveness probe fails and restarts the container.\n\nYou can configure the following probe types for readiness probes:\n\n- HTTP `GET` request: This probe sends an HTTP `GET` request to a specified port and path on the container. A response status code in the range of 200-399 indicates that the request is a success. Depending on your requirement, you can configure additional HTTP headers. The recommended approach is to create a `/healthz` or `/health` endpoint in your service for this purpose.\n- TCP connection probe: This probe attempts to open a socket to the container on the specified port. If it cannot establish a TCP connection, it becomes a failure.\n- Execute a command: This probe executes a given script inside the container. A non-zero return from the command is considered a failure. For example, `[\""cat\"", \""/tmp/healthy\""]` is considered healthy if the file `/tmp/healthy` is present. If not, it becomes a failure (non-zero exit code). In such scenarios, the application is responsible for writing and maintaining this file in the specified location.\n\nFor more details, please refer to the [Set Up Health Checks] documentation." | D15: 0.69731414 | E15: 0.37102719 | F15: 0.74434463 | G15: 0.42072307 | H15: 0.35069349 | I15: 0.54749776 | J15: 0.75830073 | O15: 0.18062155
... A45: 42 | B45: My service gets overloaded with requests how to fix this? | C45: "Implementing rate limiting on APIs in Choreo involves the following steps: Access your component from the Component Listing pane. Navigate to the Deploy section in the left menu. In the required environment card, click the view icon for the endpoint you want to apply rate limiting to. In the Endpoint Details pane, click the settings icon. Expand the Rate Limiting section under Manage. Select a Rate Limiting Level and click Apply. Choreo offers two rate-limiting levels: API-level Rate Limiting: Applies the allocated request count for the specified time unit to all operations in the API. Operation-level Rate Limiting: Allows configuring different rate-limiting values for each operation. When rate limiting is enabled, Choreo provides four response headers: x-ratelimit-limit: Shows the request count allocated for the specified time unit. x-ratelimit-reset: Indicates the time remaining to start the next rate-limiting time unit. x-ratelimit-remaining: Shows the remaining request count for the specified time unit. x-ratelimit-enforced: Appears after exceeding the allocated request count. For API Proxy components, the process differs slightly. After step 2, click the settings icon next to API Configuration and proceed directly to selecting the Rate Limiting Level." | D45: 0.20488044 | E45: 0.3194703 | F45: 0.62934121 | G45: 0.21776523 | H45: 0.46859352 | I45: 0.53362491 | J45: 0.19663335 | O45: 0.21201189

Sheet Sheet1
E1: Qwen2.5 | K1: Qwen3 | O1: GPT-4o-mini
E2: 3B | H2: 7B | K2: 4B | M2: 8B
A3: Question # | B3: Question | C3: Ground truth | D3: Copilot (GPT-4o-mini + RAG) | E3: Instruct | F3: Fine Tuned | G3: FT Simple Prompt | H3: Instruct | I3: Fine Tuned | J3: FT Simple Prompt | K3: Instruct | L3: Fine Tuned | M3: Instruct | N3: Fine Tuned
A4: 1 | B4: How to deploy a webapp? | C4: "To deploy a web application in Choreo, follow the steps below:\n\n1. **Create a project**: On the organization home page, click **+ Create Project**. Enter a display name, unique name, and description for the project. Click **Create**. This creates the project and opens the project home page. \n\n2. **Create a Web Application component**: On the project home page, click **Web Application** under **Create a Single Component**. Enter a unique name and a description for the web application. \n\n3. **Connect to GitHub**: Go to the **GitHub** tab and click **Authorize with GitHub**. If you have not already connected your GitHub repository to Choreo, enter your GitHub credentials and select the repository. You can also paste the repository URL in the **Provide Repository URL** field to connect to it without requiring authorization. \n\n4. **Enter the required information**: Enter the required information such as your GitHub account in the **Organization** field, repository name in the **Repository** field, and the branch name in the **Branch** field. \n\n5. **Select Buildpack**: Select a build Buildpack (eg: NodeJS, React, Python,PHP, etc.) as the **Buildpack** and provide the necessary details (eg: Project Directory, Language Version, Port, etc.). \n\n6. **Create the component**: Click **Create**. Choreo initializes the component with the sample implementation and opens the **Overview** page of the component.\n\n7. **Build your web application**: In the left navigation menu, click **Build**.In the Builds pane, click **Build**. This opens the Commits pane, where you can see all the commits related to the component. Select the latest commit and click **Build**. This triggers the build process and displays the progress in the **Build Logs pane**.\n\n8. **Deploy the web application**: In the left navigation menu, click **Deploy**. In the **Set Up** card, click **Configure and Deploy**. Click **Next** to move to the **Authentication Settings** pane. Keep the default settings and click **Deploy**. \n\n9. **Verify the deployment**: To verify that you have successfully hosted the web application, click the **Web App URL** in the **Development** card. This takes you to the web application." | D4: 0.45161219 | E4: 0.43186231 | F4: 0.60375922 | G4: 0.54021287 | H4: 0.60217806 | I4: 0.49406492 | J4: 0.31710898 | O4: 0.56330737
A5: 2 | B5: "How to resolve ""Module not found error"" during the deployment of a Python project?" | C5: "To resolve a **Module not found""** error during the deployment of a Python project in Choreo:\n\n1. **Verify Dependencies:**\n - Ensure all required Python modules are in `requirements.txt`\n - Example `requirements.txt`:\n ```plaintext\n flask\n requests\n numpy\n ```\n\n2. **Check File Paths:**\n - Verify that the modules and packages being imported in your Python code have the correct file paths\n\n3. **Rebuild the Component:**\n - Trigger a rebuild after updating `requirements.txt` or file paths. This will ensure that any changes made to the dependencies are included in the new build.\n\n4. **Inspect Logs:**\n - . If the error persists check build logs in Choreo Console UI for detailed error messages. The logs can provide more context on which module is not found and why. \n\n5. **Environment Configuration:**\n - Ensure correct setup of environment variables in Choreo. Sometimes environment variables might be needed for certain modules to work correctly.you can follow these steps:\n\n**Steps to Implement Custom Authentication:**\n\n1. **Add the Connection Configuration:**\n```window.configs = {\napiUrl: '<SERVICE_URL>'" | D5: 0.64233487 | E5: 0.51315699 | F5: 0.35296981 | G5: 0.36533698 | H5: 0.59319648 | I5: 0.60247963 | J5: 0.61542823 | O5: 0.8148537
A6: 3 | B6: How to add authentication to my service? | C6: "To add **authentication** to a service in **Choreo**, you can utilize **Choreo's managed authentication** or configure **custom authentication**. Here are the steps for integrating managed authentication and custom authentication:\n\n**Managed Authentication**\nManaged authentication is a feature provided by **Choreo** that simplifies the process of adding authentication and authorization to your web application. It supports web applications created with **React**, **Angular**, or **Vue.js** buildpacks.\n\n**Steps to Implement Managed Authentication:**\n\n1. **Implement Sign-in Functionality:**\n```<button onClick={() => { window.location.href = ""/auth/login"" }}>Login</button>```\nThis redirects users to the **login path** where **Choreo** handles the authentication process.\n\n2. **Obtain User Information Claims:**\n\n**Via Cookie:**\n```import Cookies from 'js-cookie';\nconst encodedUserInfo = Cookies.get('userinfo');\nconst userInfo = JSON.parse(atob(encodedUserInfo));\nCookies.remove('userinfo', { path: '/' });```\n\n**Via GET Endpoint:**\n```const response = await fetch('/auth/userinfo');```\n\n3. **Implement Sign-out Functionality:**\n```<button onClick={async () => { window.location.href = `/auth/logout?session_hint=${Cookies.get('session_hint')}`;}}>Logout</button>```\n\n4. **Invoke APIs:**\n```const response = await fetch('/choreo-apis/<api-suffix>');```\n\n**Custom Authentication**\nIf you prefer to handle authentication manually or use custom authentication mechanisms, you can follow these steps:\n\n**Steps to Implement Custom Authentication:**\n\n1. **Add the Connection Configuration:**\n```window.configs = {\napiUrl: '<SERVICE_URL>',\nconsumerKey: '<CONSUMER_KEY>',\nconsumerSecret: '<CONSUMER_SECRET>',\ntokenUrl: '<TOKEN_URL>',\n};```\n\n2. **Read the Configuration:**\n```const serviceURL = window?.configs?.apiUrl ? window.configs.apiUrl : ""/"";```\n\n3. **Acquire an OAuth 2.0 Access Token:**\n\n**Using a cURL Command:**\n```CONSUMER_KEY=""your_consumer_key""\nCONSUMER_SECRET=""your_consumer_secret""\nTOKEN_URL=""your_token_url""\nCLIENT_CREDENTIALS=$(echo -n ""$CLIENT_ID:$CLIENT_SECRET"" | base64)\ncurl -X POST $TOKEN_URL \n-H ""Content-Type: application/x-www-form-urlencoded"" \n-H ""Authorization: Basic $CLIENT_CREDENTIALS"" \n--data-urlencode ""grant_type=client_credentials""```\n\n4. **Invoke the Service:**\n```const response = await axios.get(serviceURL/{RESOURCE_PATH}, {\nheaders: {\n'Authorization': `Bearer ${accessToken}`\n}\n});```\n\nBy following these steps, you can successfully add **authentication** to your service in **Choreo** using either **managed authentication** or **custom authentication** methods." | D6: 0.5218856 | E6: 0.55498103 | F6: 0.47240955 | G6: 0.38364679 | H6: 0.47355567 | I6: 0.36336236 | J6: 0.62821353 | O6: 0.3729687
A7: 4 | B7: How to add a custom domain to my web app? | C7: "to add a custom domain to a web app in Choreo:\n\nPrerequisites:\n1. Ensure you have organization administrator privileges.\n2. Make sure your web app is deployed in the desired environment.\n\nSteps to Add a Custom Domain:\n1. **Sign in to the Choreo Console**.\n2. **Access Organization Settings**:\n * Click the **Organization** list in the Choreo Console header.\n * In the left navigation menu, click **Settings**.\n * Go to the **URL Settings** tab and then click the **Active Domains** tab.\n3. **Add the Custom Domain**:\n * Click **+ Add Domains**.\n * In the **Add a Custom Domain** pane, enter your domain name.\n * Select the environment where you want to apply the domain name.\n * Select the entity type as **Web App**.\n * Note the generated CNAME target value displayed and create a DNS record associating your domain name to the CNAME target value with your DNS provider.\n4. **Verify the Domain**:\n * Once the CNAME type DNS record is created, click **Verify**.\n5. **Configure TLS Certificates**:\n * On successful verification, click **Next**.\n * Select a TLS certificate provider. You can either import your own TLS certificates or allow Choreo to generate and manage the certificates using **Let's Encrypt**.\n6. **Save the Custom Domain**:\n * Click **Add** to save the custom domain.\n\nConfigure a Custom URL for Your Web App:\n1. **Request a Custom URL**:\n * Sign in to the Choreo Console.\n * In the **Component Listing** pane, click on your web app.\n * Click **Settings** in the left navigation menu.\n * Go to the **URL Settings** tab. If an active custom domain is available, the **Edit URL Mapping** icon in the corresponding **Action** column will be enabled.\n2. **Configure the URL**:\n * Click the **Edit URL Mapping** icon under the **Action** column for the desired environment.\n * Select the domain from the **Domain** drop-down list.\n * Click **Configure** to create the custom URL mapping. The custom URL request will be in **Pending** status until approved by an organization administrator.\n3. **Approval**:\n * The organization administrator needs to approve the custom URL request from the organization-level settings page under the **Pending URL Requests** tab.\n\nOnce the custom URL request is approved, the custom domain will be applied to your web app." | D7: 0.75544753 | E7: 0.40244704 | F7: 0.68007699 | G7: 0.56626809 | H7: 0.43524436 | I7: 0.46143685 | J7: 0.60595921 | O7: 0.53727208
A8: 5 | B8: How can I test my service? | C8: "To test your service in **Choreo**, you can use the integrated **OpenAPI Console** within the **Choreo Console UI**. Here are the detailed steps to perform the test:\n\n**Steps to Test the Service in Choreo Console**\n\n1. **Navigate to the Test Console**:\n - In the **Choreo Console** left navigation menu, click **Test** and then click **Console**.\n\n2. **Select the Environment**:\n - In the **OpenAPI Console** that opens, select **Development** from the environment drop-down list.\n\n3. **Choose the Endpoint**:\n - In the **Endpoint** list, select the relevant **REST endpoint** for your service.\n\n4. **Test the GET Method**:\n - Expand the **GET /** method (e.g., **GET /books**).\n - Click **Try it out**.\n - Click **Execute**.\n - Check the **Server Response** section to see the response from the server.\n\n5. **Test the POST Method**:\n - Expand the **POST /** method (e.g., **POST /books**).\n - Click **Try it out**.\n - Update the **request body** with the necessary parameters. For example:\n ```\n {\n ""author"": ""Your Author"",\n ""status"": ""to_read"",\n ""title"": ""Your Title""\n }\n ```\n - Click **Execute**.\n - Check the **Server Response** section. On successful invocation, you should receive a **201 HTTP status code**.\n\n6. **Additional Methods**:\n - Similarly, you can expand and test other methods (e.g., **PUT**, **DELETE**) available for your service by following the **Try it out** and **Execute** steps." | D8: 0.63864487 | E8: 0.41655397 | F8: 0.34881003 | G8: 0.65767423 | H8: 0.25406 | I8: 0.41350118 | J8: 0.7040307 | O8: 0.60197541
A9: 6 | B9: How can I add environment variables to python webapp? | C9: "To set up environment variables in **Choreo**, follow these steps:\n\n**Steps to Apply Environment Variables**\n\n1. **Navigate to Your Component in Choreo Console**:\n - Go to the **Component Listing** pane and click on the component you want to configure.\n\n2. Access **Configurations & Secrets**:\n - In the left navigation menu, click **DevOps** and then click **Configs & Secrets**.\n\n3. **Create a New Environment Variable**:\n - Click **+ Create**.\n - In the **Create a Config or Secret** pane, select **Environment Variables**.\n\n4. **Mark as a Secret (Optional)**:\n - If you need the environment variable values to be secrets, select **Mark as a Secret**. Note that you will not be able to read these values after setting them.\n\n5. **Specify the Environment Variables**:\n - Enter the **Display Name** for your configuration or secret.\n - Under **Add Environment Variables**, specify the environment variables as **key-value pairs**.\n - Click **Add Item** to add more variables if needed.\n\n6. **Finalize Creation**:\n - Click **Create** to save your environment variables.\n\n**Additional Tips**\n\n- **Ballerina Configurables**: If you are dealing with Ballerina components, you can manage configurables separately. Configurables can be used instead of environment variables for file mounts in Ballerina components. \n\n**Security Note**\n\n- All configurations and secrets are stored in an encrypted secret vault managed by **WSO2** in the cloud data plane. If you are on a private data plane, they are stored in an **Azure key vault** or **AWS secret manager** attached to your data plane in your cloud environment." | D9: 0.83173597 | E9: 0.1998654 | F9: 0.62108826 | G9: 0.62579738 | H9: 0.42395524 | I9: 0.36585057 | J9: 0.64616411 | O9: 0.69454882
A10: 7 | B10: How to connect the React frontend to the backend? | C10: "1: Create and Deploy Your Backend Service\nFirst, ensure your backend service is deployed in Choreo. If you don't have a service yet, you can create one by following these steps:\n1. **Connect to Your Repository:**\n * On the project home page, click **Start** under **Create Multiple Components**.\n * Go to the **GitHub** tab and authorize Choreo to connect to your GitHub account.\n * Enter the repository URL and branch details.\n * Select and configure the backend service component.\n2. **Build and Deploy the Service:**\n * Click the service component listed under **Component Listing** on the project home page.\n * In the left navigation menu, click **Build** and then **Build Latest**.\n * Once the build is complete, proceed to deploy the service.\n\nStep 2: Create a React Frontend Application in Choreo\nNext, create a web application component for your React frontend:\n1. **Create the Web Application Component:**\n * In the Choreo Console header, select your project.\n * Click **+ Create** under **Component Listing**.\n * Select **Web Application** and fill in the necessary details (display name, unique name, description).\n * Authorize with GitHub to connect your repository.\n * Enter your GitHub account, repository, and branch details.\n * Select **React** as the buildpack.\n * Enter the build configuration details (`Project Directory`, `Build Command`, `Build Path`, `Node Version`).\n2. **Build the Web Application Component:**\n * In the left navigation menu, click **Build** and then **Build Latest**.\n\nStep 3: Connect the Web Application to the Backend Service\nTo establish a connection between your React frontend and the backend service:\n1. **Create a Connection:**\n * In the left navigation menu, click **Dependencies** and then **Connections**.\n * Click **+ Create** and select your backend service.\n * Provide a name and description for the connection and click **Create**.\n * Copy the service URL displayed for the Development environment.\n2. **Configure the Web Application:**\n * In the left navigation menu, click **Deploy** and then **Configure and Deploy**.\n * In the `config.js` file mount, replace `<Service URL>` with the copied service URL:\n ```javascript\n window.configs = {\n apiUrl: '<Service URL>',\n };\n ```\n * Ensure managed authentication is enabled and configure authentication settings (Post Login Path, Post Logout Path, Error Path).\n3. **Deploy the Web Application:**\n * Click **Deploy** in the **Authentication** pane.\n * Once deployed, copy the **Web App URL**.\n\nStep 4: Access and Test Your Application\n* Navigate to the web app URL to verify that your React frontend is successfully connected to the backend service." | D10: 0.5442786 | E10: 0.37390651 | F10: 0.60726461 | G10: 0.40124921 | H10: 0.36998305 | I10: 0.46863383 | J10: 0.42201258 | O10: 0.53432761
A11: 8 | B11: How can I deploy my backend and then connect it to the frontend deployed in github pages? | C11: "To deploy a backend service on Choreo and connect it to a frontend hosted on GitHub Pages, follow these steps:\n\nStep 1: Deploy the Backend Service on Choreo\n1. Create a Project in Choreo:\n * Go to the Choreo Console and sign in.\n * On the organization home page, click **+ Create Project**.\n * Enter a display name, unique name, and description for the project.\n * Click **Create** to create the project and open the project home page.\n\n2. Connect Your GitHub Repository and Configure the Service:\n * On the project home page, click **Start** under **Create Multiple Components**.\n * Go to the **GitHub** tab.\n * Click **Authorize with GitHub** to allow Choreo to connect to your GitHub account.\n * Enter the GitHub account details, repository, and branch.\n * In the **Add Component Directories** pane, click the + icon corresponding to your backend service directory.\n * Configure the service component by specifying details such as Component Display Name, Component Name, Path, Component Type, Buildpack, and Language Version.\n * Click **Save** and then **Finish** to initialize the service.\n\n3. Build and deploy the service\n 3.1: Build\n * On the project home page, click the service component you created. This takes you to the component overview page.\n * In the left navigation, click **Build**.\n * Click **Build Latest**. The build process may take a while, and you can track the progress via the logs in the Build Details pane.\n * Once the build process is complete, the build status changes to Success.\n\n 3.2: Deploy\n * In the left navigation menu, click **Deploy**.\n * On the **Set Up** card, click **Configure & Deploy**.\n * In the **Environment Configurations** pane, click **Next**.\n * In the **File Mount** pane, click **Next**.\n * Review the **Endpoint Details** and click **Deploy**. In the Endpoint Details pane that opens, ensure that the Network Visibility is set to Public. This setting securely exposes the endpoint for external consumption.\n * The deployment process may take some time, and you can track the progress by observing the logs.\n * Once the deployment is complete, the build status changes to Active on the Development environment card.\n\n Ensure that your backend service is configured to allow CORS (Cross-Origin Resource Sharing) requests from your frontend's domain (GitHub Pages). \n This is crucial for enabling communication between the two different domains.\n To do that follow these steps\n\n 3.3.: Enable CORS\n * From your Development card access endpoint details. \n * In the Endpoint Details pane Go to settings. \n * From the security tab in the settings you can allow CORS.\n\nTo connect your service to the frontend deployed outside choreo in this case github pages you need to get the public url for your service.\n\n4. Getting the Public URL:\n * Once the deployment is complete, navigate to the component overview page where you can find the service URL.\n * Copy the public URL of the service from the development environment card.\n\n5. Then you have to manually add this public URL as the API URL in your frontend code.\n Use this API URL in your frontend to make HTTP requests (e.g., GET, POST) to interact with your backend service." | D11: 0.46449408 | E11: 0.46815158 | F11: 0.31490862 | G11: 0.48149296 | H11: 0.28746816 | I11: 0.28646211 | J11: 0.52075165 | O11: 0.66662917
A12: 9 | B12: How can I implement testing for a full-stack application including automated testing for both frontend and backend components? | C12: "To implement automated testing for both frontend and backend components in a full-stack application using Choreo, follow these steps:\n\n**Backend Testing with Test Runner**\n\n**Create a Test Runner Component:**\n1. Go to the Choreo Console.\n2. **Click `+Create`** in the Component Listing section.\n3.Select **`Test Runner`.**\n4. Enter a unique name and description for the test runner component.\n5. Go to the `GitHub` tab and enter:\n - **GitHub Account**\n - **GitHub Repository**\n - **Branch**\n6. Select a buildpack based on the language of your choice.\n7. Enter the relevant values based on the selected buildpack.\n8. **Click `Create`.\n**Build and Deploy the Test Runner Component:**\n1. Navigate to `Build` on the left panel.\n2. **Click `Build`** and select the latest commit.\n3. Once the build completes, go to `Deploy`.\n4. **Click `Deploy`** to deploy the Test Runner component, or use `Configure and Deploy` for additional configurations.\n5. After deployment, go to `Execute` and select the environment.\n6. **Click `Run Now`** to trigger the test execution.\n7. Once execution is completed, click on a particular execution to view the test results.\n\n**Frontend Testing**\n\n**Access and Test Frontend Application:**\n1. Access the frontend application via its web URL.\n2. Perform manual testing by interacting with the application (e.g., adding items, checking user-specific data)." | D12: 0.39356339 | E12: 0.55611733 | F12: 0.54498796 | G12: 0.51247423 | H12: 0.39504649 | I12: 0.20334512 | J12: 0.36180657 | O12: 0.186414
A13: 10 | B13: "I'm getting ""procfile not found"" error for my python service. How do I resolve this?" | C13: "The error you're encountering is because Choreo requires a `Procfile` in your Python project's root directory. A `Procfile` is a configuration file used to declare the commands that are run by your application's containers. \n\nFor a Python project, your `Procfile` might look something like this:\n```\nweb: <command to start your application>\n``` \nFor example, if you're using Flask, your `Procfile` should look like this:\n```\nweb: flask run --host=0.0.0.0\n```\n\nPlease ensure that you have a `Procfile` in your project root directory and that it contains the appropriate command to start your application. You can refer more on this from the [Choreo documentation](https://wso2.com/choreo/docs/develop-components/deploy-an-application-with-buildpacks/#develop-a-component)." | D13: 0.9682382 | E13: 0.37482335 | F13: 0.21157165 | G13: 0.4046615 | H13: 0.55401302 | I13: 0.63217688 | J13: 0.66214098 | O13: 0.53408446
A14: 11 | B14: I'm getting .choreo/endpoints.yaml not found error. How do I resolve this? | C14: "The error message you're seeing, '.choreo/endpoints.yaml not found', indicates that the `endpoints.yaml` file is missing from your project's root directory in the `.choreo` folder. This file is required to define the endpoints for your service component. \n\nTo resolve this error, you need to create an `endpoints.yaml` file in the `.choreo` directory at the build context path and commit it to the source repository. The `endpoints.yaml` file should contain details about the endpoints that your service component will expose. Here is a sample `endpoints.yaml` file:\n\n```yaml\nversion: 0.1\nendpoints:\n- name: Your Service\n port: 9090\n type: REST\n networkVisibility: Project\n context: /your_service\n schemaFilePath: your_service_openapi.yaml\n```\n\nIn this file:\n\n- `name` is a unique name for the endpoint, which Choreo will use to generate the managed API.\n- `port` is the numeric port value that gets exposed via this endpoint.\n- `type` is the type of traffic this endpoint is accepting, such as `REST`, `GraphQL`, `gRPC`, `UDP`or `TCP`.\n- `networkVisibility` is the network level visibility of this endpoint, which defaults to `Public` if not specified. Accepted values are `Project`, `Organization`, or `Public`.\n- `context` is the context (base path) of the API that Choreo exposes via this endpoint. \n- `schemaFilePath` is the swagger definition file path. This field should be a relative path to the project path.\n\nPlease make sure to replace 'Your Service' and '/your_service' with the actual name and context of your service, and 'your_service_openapi.yaml' with the actual OpenAPI schema file.\n\nFor more detailed information about the `endpoints.yaml` file and its structure, you can refer to the following documentation" | D14: 0.98787901 | E14: 0.6304051 | F14: 0.73697389 | G14: 0.66229412 | H14: 0.68957303 | I14: 0.63804073 | J14: 0.21798168 | O14: 0.59667606
A15: 12 | B15: Tell me how I can configure a readiness probe? | C15: "To configure a readiness probe in Choreo, follow these steps:\n\n1. In the **Component Listing** pane, click on the component for which you want to configure readiness probes.\n2. In the left navigation menu, click **DevOps** and then click **Health Checks**.\n3. On the **Health Checks** page, click **+ Create**.\n4. Configure the readiness probe depending on your requirement.\n5. Click **Save**. \n\nYou can update or remove a probe at any time. After setting up the probe, you can ensure that the container works as expected by clicking **Runtime** under **DevOps** in the left navigation menu. On the **Runtime** page, check the details to confirm that the container works as expected. If the container does not start, check the **events and conditions** to see if any of the probes are causing the container to fail.\n\nReadiness probes run periodically throughout the lifecycle of a container. Unlike liveness probes, these probes do not restart the container if the probe fails. Instead, they stop the container from receiving network traffic. Be mindful when you configure readiness probes on a single-running replica. If the readiness probe fails, your application stops receiving traffic because there is only one active replica. The application may not recover unless the liveness probe fails and restarts the container.\n\nYou can configure the following probe types for readiness probes:\n\n- HTTP `GET` request: This probe sends an HTTP `GET` request to a specified port and path on the container. A response status code in the range of 200-399 indicates that the request is a success. Depending on your requirement, you can configure additional HTTP headers. The recommended approach is to create a `/healthz` or `/health` endpoint in your service for this purpose.\n- TCP connection probe: This probe attempts to open a socket to the container on the specified port. If it cannot establish a TCP connection, it becomes a failure.\n- Execute a command: This probe executes a given script inside the container. A non-zero return from the command is considered a failure. For example, `[\""cat\"", \""/tmp/healthy\""]` is considered healthy if the file `/tmp/healthy` is present. If not, it becomes a failure (non-zero exit code). In such scenarios, the application is responsible for writing and maintaining this file in the specified location.\n\nFor more details, please refer to the [Set Up Health Checks] documentation." | D15: 0.73018711 | E15: 0.41031291 | F15: 0.84673691 | G15: 0.58640083 | H15: 0.5589186 | I15: 0.65429747 | J15: 0.47399288 | O15: 0.18062155
... A45: 42 | B45: My service gets overloaded with requests how to fix this? | C45: "Implementing rate limiting on APIs in Choreo involves the following steps: Access your component from the Component Listing pane. Navigate to the Deploy section in the left menu. In the required environment card, click the view icon for the endpoint you want to apply rate limiting to. In the Endpoint Details pane, click the settings icon. Expand the Rate Limiting section under Manage. Select a Rate Limiting Level and click Apply. Choreo offers two rate-limiting levels: API-level Rate Limiting: Applies the allocated request count for the specified time unit to all operations in the API. Operation-level Rate Limiting: Allows configuring different rate-limiting values for each operation. When rate limiting is enabled, Choreo provides four response headers: x-ratelimit-limit: Shows the request count allocated for the specified time unit. x-ratelimit-reset: Indicates the time remaining to start the next rate-limiting time unit. x-ratelimit-remaining: Shows the remaining request count for the specified time unit. x-ratelimit-enforced: Appears after exceeding the allocated request count. For API Proxy components, the process differs slightly. After step 2, click the settings icon next to API Configuration and proceed directly to selecting the Rate Limiting Level." | D45: 0.20490031 | E45: 0.40536638 | F45: 0.54604952 | G45: 0.21765034 | H45: 0.46390658 | I45: 0.52030628 | J45: 0.19663335 | O45: 0.29148108

Sheet Semantic Similarity (Ada 002)
E1: Qwen2.5 | K1: Qwen3 | O1: GPT-4o-mini (no RAG)
E2: 3B | H2: 7B | K2: 4B | M2: 8B
A3: Question # | B3: Question | C3: Ground truth | D3: Copilot (GPT-4o-mini + RAG) | E3: Instruct | F3: Fine Tuned | G3: FT Simple Prompt | H3: Instruct | I3: Fine Tuned | J3: FT Simple Prompt | K3: Instruct | L3: Fine Tuned | M3: Instruct | N3: Fine Tuned
A4: 1 | B4: How to deploy a webapp? | C4: "To deploy a web application in Choreo, follow the steps below:\n\n1. **Create a project**: On the organization home page, click **+ Create Project**. Enter a display name, unique name, and description for the project. Click **Create**. This creates the project and opens the project home page. \n\n2. **Create a Web Application component**: On the project home page, click **Web Application** under **Create a Single Component**. Enter a unique name and a description for the web application. \n\n3. **Connect to GitHub**: Go to the **GitHub** tab and click **Authorize with GitHub**. If you have not already connected your GitHub repository to Choreo, enter your GitHub credentials and select the repository. You can also paste the repository URL in the **Provide Repository URL** field to connect to it without requiring authorization. \n\n4. **Enter the required information**: Enter the required information such as your GitHub account in the **Organization** field, repository name in the **Repository** field, and the branch name in the **Branch** field. \n\n5. **Select Buildpack**: Select a build Buildpack (eg: NodeJS, React, Python,PHP, etc.) as the **Buildpack** and provide the necessary details (eg: Project Directory, Language Version, Port, etc.). \n\n6. **Create the component**: Click **Create**. Choreo initializes the component with the sample implementation and opens the **Overview** page of the component.\n\n7. **Build your web application**: In the left navigation menu, click **Build**.In the Builds pane, click **Build**. This opens the Commits pane, where you can see all the commits related to the component. Select the latest commit and click **Build**. This triggers the build process and displays the progress in the **Build Logs pane**.\n\n8. **Deploy the web application**: In the left navigation menu, click **Deploy**. In the **Set Up** card, click **Configure and Deploy**. Click **Next** to move to the **Authentication Settings** pane. Keep the default settings and click **Deploy**. \n\n9. **Verify the deployment**: To verify that you have successfully hosted the web application, click the **Web App URL** in the **Development** card. This takes you to the web application." | D4: 0.96434351 | E4: 0.90926743 | F4: 0.96049141 | G4: 0.92275624 | H4: 0.90871223 | I4: 0.94177692 | J4: 0.94116321 | O4: 0.94413858
A5: 2 | B5: "How to resolve ""Module not found error"" during the deployment of a Python project?" | C5: "To resolve a **Module not found""** error during the deployment of a Python project in Choreo:\n\n1. **Verify Dependencies:**\n - Ensure all required Python modules are in `requirements.txt`\n - Example `requirements.txt`:\n ```plaintext\n flask\n requests\n numpy\n ```\n\n2. **Check File Paths:**\n - Verify that the modules and packages being imported in your Python code have the correct file paths\n\n3. **Rebuild the Component:**\n - Trigger a rebuild after updating `requirements.txt` or file paths. This will ensure that any changes made to the dependencies are included in the new build.\n\n4. **Inspect Logs:**\n - . If the error persists check build logs in Choreo Console UI for detailed error messages. The logs can provide more context on which module is not found and why. \n\n5. **Environment Configuration:**\n - Ensure correct setup of environment variables in Choreo. Sometimes environment variables might be needed for certain modules to work correctly.you can follow these steps:\n\n**Steps to Implement Custom Authentication:**\n\n1. **Add the Connection Configuration:**\n```window.configs = {\napiUrl: '<SERVICE_URL>'" | D5: 0.93297585 | E5: 0.88181039 | F5: 0.86642471 | G5: 0.89884793 | H5: 0.91332647 | I5: 0.90991854 | J5: 0.90615737 | O5: 0.93288419
A6: 3 | B6: How to add authentication to my service? | C6: "To add **authentication** to a service in **Choreo**, you can utilize **Choreo's managed authentication** or configure **custom authentication**. Here are the steps for integrating managed authentication and custom authentication:\n\n**Managed Authentication**\nManaged authentication is a feature provided by **Choreo** that simplifies the process of adding authentication and authorization to your web application. It supports web applications created with **React**, **Angular**, or **Vue.js** buildpacks.\n\n**Steps to Implement Managed Authentication:**\n\n1. **Implement Sign-in Functionality:**\n```<button onClick={() => { window.location.href = ""/auth/login"" }}>Login</button>```\nThis redirects users to the **login path** where **Choreo** handles the authentication process.\n\n2. **Obtain User Information Claims:**\n\n**Via Cookie:**\n```import Cookies from 'js-cookie';\nconst encodedUserInfo = Cookies.get('userinfo');\nconst userInfo = JSON.parse(atob(encodedUserInfo));\nCookies.remove('userinfo', { path: '/' });```\n\n**Via GET Endpoint:**\n```const response = await fetch('/auth/userinfo');```\n\n3. **Implement Sign-out Functionality:**\n```<button onClick={async () => { window.location.href = `/auth/logout?session_hint=${Cookies.get('session_hint')}`;}}>Logout</button>```\n\n4. **Invoke APIs:**\n```const response = await fetch('/choreo-apis/<api-suffix>');```\n\n**Custom Authentication**\nIf you prefer to handle authentication manually or use custom authentication mechanisms, you can follow these steps:\n\n**Steps to Implement Custom Authentication:**\n\n1. **Add the Connection Configuration:**\n```window.configs = {\napiUrl: '<SERVICE_URL>',\nconsumerKey: '<CONSUMER_KEY>',\nconsumerSecret: '<CONSUMER_SECRET>',\ntokenUrl: '<TOKEN_URL>',\n};```\n\n2. **Read the Configuration:**\n```const serviceURL = window?.configs?.apiUrl ? window.configs.apiUrl : ""/"";```\n\n3. **Acquire an OAuth 2.0 Access Token:**\n\n**Using a cURL Command:**\n```CONSUMER_KEY=""your_consumer_key""\nCONSUMER_SECRET=""your_consumer_secret""\nTOKEN_URL=""your_token_url""\nCLIENT_CREDENTIALS=$(echo -n ""$CLIENT_ID:$CLIENT_SECRET"" | base64)\ncurl -X POST $TOKEN_URL \n-H ""Content-Type: application/x-www-form-urlencoded"" \n-H ""Authorization: Basic $CLIENT_CREDENTIALS"" \n--data-urlencode ""grant_type=client_credentials""```\n\n4. **Invoke the Service:**\n```const response = await axios.get(serviceURL/{RESOURCE_PATH}, {\nheaders: {\n'Authorization': `Bearer ${accessToken}`\n}\n});```\n\nBy following these steps, you can successfully add **authentication** to your service in **Choreo** using either **managed authentication** or **custom authentication** methods." | D6: 0.93860623 | E6: 0.90742414 | F6: 0.88963819 | G6: 0.89173001 | H6: 0.89422268 | I6: 0.8874117 | J6: 0.89746952 | O6: 0.90363952
A7: 4 | B7: How to add a custom domain to my web app? | C7: "to add a custom domain to a web app in Choreo:\n\nPrerequisites:\n1. Ensure you have organization administrator privileges.\n2. Make sure your web app is deployed in the desired environment.\n\nSteps to Add a Custom Domain:\n1. **Sign in to the Choreo Console**.\n2. **Access Organization Settings**:\n * Click the **Organization** list in the Choreo Console header.\n * In the left navigation menu, click **Settings**.\n * Go to the **URL Settings** tab and then click the **Active Domains** tab.\n3. **Add the Custom Domain**:\n * Click **+ Add Domains**.\n * In the **Add a Custom Domain** pane, enter your domain name.\n * Select the environment where you want to apply the domain name.\n * Select the entity type as **Web App**.\n * Note the generated CNAME target value displayed and create a DNS record associating your domain name to the CNAME target value with your DNS provider.\n4. **Verify the Domain**:\n * Once the CNAME type DNS record is created, click **Verify**.\n5. **Configure TLS Certificates**:\n * On successful verification, click **Next**.\n * Select a TLS certificate provider. You can either import your own TLS certificates or allow Choreo to generate and manage the certificates using **Let's Encrypt**.\n6. **Save the Custom Domain**:\n * Click **Add** to save the custom domain.\n\nConfigure a Custom URL for Your Web App:\n1. **Request a Custom URL**:\n * Sign in to the Choreo Console.\n * In the **Component Listing** pane, click on your web app.\n * Click **Settings** in the left navigation menu.\n * Go to the **URL Settings** tab. If an active custom domain is available, the **Edit URL Mapping** icon in the corresponding **Action** column will be enabled.\n2. **Configure the URL**:\n * Click the **Edit URL Mapping** icon under the **Action** column for the desired environment.\n * Select the domain from the **Domain** drop-down list.\n * Click **Configure** to create the custom URL mapping. The custom URL request will be in **Pending** status until approved by an organization administrator.\n3. **Approval**:\n * The organization administrator needs to approve the custom URL request from the organization-level settings page under the **Pending URL Requests** tab.\n\nOnce the custom URL request is approved, the custom domain will be applied to your web app." | D7: 0.96464727 | E7: 0.87509429 | F7: 0.96168726 | G7: 0.96072452 | H7: 0.93500728 | I7: 0.95213037 | J7: 0.96042219 | O7: 0.94908831
A8: 5 | B8: How can I test my service? | C8: "To test your service in **Choreo**, you can use the integrated **OpenAPI Console** within the **Choreo Console UI**. Here are the detailed steps to perform the test:\n\n**Steps to Test the Service in Choreo Console**\n\n1. **Navigate to the Test Console**:\n - In the **Choreo Console** left navigation menu, click **Test** and then click **Console**.\n\n2. **Select the Environment**:\n - In the **OpenAPI Console** that opens, select **Development** from the environment drop-down list.\n\n3. **Choose the Endpoint**:\n - In the **Endpoint** list, select the relevant **REST endpoint** for your service.\n\n4. **Test the GET Method**:\n - Expand the **GET /** method (e.g., **GET /books**).\n - Click **Try it out**.\n - Click **Execute**.\n - Check the **Server Response** section to see the response from the server.\n\n5. **Test the POST Method**:\n - Expand the **POST /** method (e.g., **POST /books**).\n - Click **Try it out**.\n - Update the **request body** with the necessary parameters. For example:\n ```\n {\n ""author"": ""Your Author"",\n ""status"": ""to_read"",\n ""title"": ""Your Title""\n }\n ```\n - Click **Execute**.\n - Check the **Server Response** section. On successful invocation, you should receive a **201 HTTP status code**.\n\n6. **Additional Methods**:\n - Similarly, you can expand and test other methods (e.g., **PUT**, **DELETE**) available for your service by following the **Try it out** and **Execute** steps." | D8: 0.95457946 | E8: 0.88843811 | F8: 0.88460184 | G8: 0.89992768 | H8: 0.91279172 | I8: 0.88477396 | J8: 0.89159449 | O8: 0.90790164
A9: 6 | B9: How can I add environment variables to python webapp? | C9: "To set up environment variables in **Choreo**, follow these steps:\n\n**Steps to Apply Environment Variables**\n\n1. **Navigate to Your Component in Choreo Console**:\n - Go to the **Component Listing** pane and click on the component you want to configure.\n\n2. Access **Configurations & Secrets**:\n - In the left navigation menu, click **DevOps** and then click **Configs & Secrets**.\n\n3. **Create a New Environment Variable**:\n - Click **+ Create**.\n - In the **Create a Config or Secret** pane, select **Environment Variables**.\n\n4. **Mark as a Secret (Optional)**:\n - If you need the environment variable values to be secrets, select **Mark as a Secret**. Note that you will not be able to read these values after setting them.\n\n5. **Specify the Environment Variables**:\n - Enter the **Display Name** for your configuration or secret.\n - Under **Add Environment Variables**, specify the environment variables as **key-value pairs**.\n - Click **Add Item** to add more variables if needed.\n\n6. **Finalize Creation**:\n - Click **Create** to save your environment variables.\n\n**Additional Tips**\n\n- **Ballerina Configurables**: If you are dealing with Ballerina components, you can manage configurables separately. Configurables can be used instead of environment variables for file mounts in Ballerina components. \n\n**Security Note**\n\n- All configurations and secrets are stored in an encrypted secret vault managed by **WSO2** in the cloud data plane. If you are on a private data plane, they are stored in an **Azure key vault** or **AWS secret manager** attached to your data plane in your cloud environment." | D9: 0.92694386 | E9: 0.79946159 | F9: 0.8925163 | G9: 0.89343343 | H9: 0.86248761 | I9: 0.84801767 | J9: 0.91798977 | O9: 0.86330165
A10: 7 | B10: How to connect the React frontend to the backend? | C10: "1: Create and Deploy Your Backend Service\nFirst, ensure your backend service is deployed in Choreo. If you don't have a service yet, you can create one by following these steps:\n1. **Connect to Your Repository:**\n * On the project home page, click **Start** under **Create Multiple Components**.\n * Go to the **GitHub** tab and authorize Choreo to connect to your GitHub account.\n * Enter the repository URL and branch details.\n * Select and configure the backend service component.\n2. **Build and Deploy the Service:**\n * Click the service component listed under **Component Listing** on the project home page.\n * In the left navigation menu, click **Build** and then **Build Latest**.\n * Once the build is complete, proceed to deploy the service.\n\nStep 2: Create a React Frontend Application in Choreo\nNext, create a web application component for your React frontend:\n1. **Create the Web Application Component:**\n * In the Choreo Console header, select your project.\n * Click **+ Create** under **Component Listing**.\n * Select **Web Application** and fill in the necessary details (display name, unique name, description).\n * Authorize with GitHub to connect your repository.\n * Enter your GitHub account, repository, and branch details.\n * Select **React** as the buildpack.\n * Enter the build configuration details (`Project Directory`, `Build Command`, `Build Path`, `Node Version`).\n2. **Build the Web Application Component:**\n * In the left navigation menu, click **Build** and then **Build Latest**.\n\nStep 3: Connect the Web Application to the Backend Service\nTo establish a connection between your React frontend and the backend service:\n1. **Create a Connection:**\n * In the left navigation menu, click **Dependencies** and then **Connections**.\n * Click **+ Create** and select your backend service.\n * Provide a name and description for the connection and click **Create**.\n * Copy the service URL displayed for the Development environment.\n2. **Configure the Web Application:**\n * In the left navigation menu, click **Deploy** and then **Configure and Deploy**.\n * In the `config.js` file mount, replace `<Service URL>` with the copied service URL:\n ```javascript\n window.configs = {\n apiUrl: '<Service URL>',\n };\n ```\n * Ensure managed authentication is enabled and configure authentication settings (Post Login Path, Post Logout Path, Error Path).\n3. **Deploy the Web Application:**\n * Click **Deploy** in the **Authentication** pane.\n * Once deployed, copy the **Web App URL**.\n\nStep 4: Access and Test Your Application\n* Navigate to the web app URL to verify that your React frontend is successfully connected to the backend service." | D10: 0.9271144 | E10: 0.87797898 | F10: 0.92905844 | G10: 0.91647224 | H10: 0.9174322 | I10: 0.90679339 | J10: 0.93805032 | O10: 0.93731043
A11: 8 | B11: How can I deploy my backend and then connect it to the frontend deployed in github pages? | C11: "To deploy a backend service on Choreo and connect it to a frontend hosted on GitHub Pages, follow these steps:\n\nStep 1: Deploy the Backend Service on Choreo\n1. Create a Project in Choreo:\n * Go to the Choreo Console and sign in.\n * On the organization home page, click **+ Create Project**.\n * Enter a display name, unique name, and description for the project.\n * Click **Create** to create the project and open the project home page.\n\n2. Connect Your GitHub Repository and Configure the Service:\n * On the project home page, click **Start** under **Create Multiple Components**.\n * Go to the **GitHub** tab.\n * Click **Authorize with GitHub** to allow Choreo to connect to your GitHub account.\n * Enter the GitHub account details, repository, and branch.\n * In the **Add Component Directories** pane, click the + icon corresponding to your backend service directory.\n * Configure the service component by specifying details such as Component Display Name, Component Name, Path, Component Type, Buildpack, and Language Version.\n * Click **Save** and then **Finish** to initialize the service.\n\n3. Build and deploy the service\n 3.1: Build\n * On the project home page, click the service component you created. This takes you to the component overview page.\n * In the left navigation, click **Build**.\n * Click **Build Latest**. The build process may take a while, and you can track the progress via the logs in the Build Details pane.\n * Once the build process is complete, the build status changes to Success.\n\n 3.2: Deploy\n * In the left navigation menu, click **Deploy**.\n * On the **Set Up** card, click **Configure & Deploy**.\n * In the **Environment Configurations** pane, click **Next**.\n * In the **File Mount** pane, click **Next**.\n * Review the **Endpoint Details** and click **Deploy**. In the Endpoint Details pane that opens, ensure that the Network Visibility is set to Public. This setting securely exposes the endpoint for external consumption.\n * The deployment process may take some time, and you can track the progress by observing the logs.\n * Once the deployment is complete, the build status changes to Active on the Development environment card.\n\n Ensure that your backend service is configured to allow CORS (Cross-Origin Resource Sharing) requests from your frontend's domain (GitHub Pages). \n This is crucial for enabling communication between the two different domains.\n To do that follow these steps\n\n 3.3.: Enable CORS\n * From your Development card access endpoint details. \n * In the Endpoint Details pane Go to settings. \n * From the security tab in the settings you can allow CORS.\n\nTo connect your service to the frontend deployed outside choreo in this case github pages you need to get the public url for your service.\n\n4. Getting the Public URL:\n * Once the deployment is complete, navigate to the component overview page where you can find the service URL.\n * Copy the public URL of the service from the development environment card.\n\n5. Then you have to manually add this public URL as the API URL in your frontend code.\n Use this API URL in your frontend to make HTTP requests (e.g., GET, POST) to interact with your backend service." | D11: 0.95231596 | E11: 0.94302884 | F11: 0.91677736 | G11: 0.94089719 | H11: 0.87714538 | I11: 0.93532213 | J11: 0.94014946 | O11: 0.95223096
A12: 9 | B12: How can I implement testing for a full-stack application including automated testing for both frontend and backend components? | C12: "To implement automated testing for both frontend and backend components in a full-stack application using Choreo, follow these steps:\n\n**Backend Testing with Test Runner**\n\n**Create a Test Runner Component:**\n1. Go to the Choreo Console.\n2. **Click `+Create`** in the Component Listing section.\n3.Select **`Test Runner`.**\n4. Enter a unique name and description for the test runner component.\n5. Go to the `GitHub` tab and enter:\n - **GitHub Account**\n - **GitHub Repository**\n - **Branch**\n6. Select a buildpack based on the language of your choice.\n7. Enter the relevant values based on the selected buildpack.\n8. **Click `Create`.\n**Build and Deploy the Test Runner Component:**\n1. Navigate to `Build` on the left panel.\n2. **Click `Build`** and select the latest commit.\n3. Once the build completes, go to `Deploy`.\n4. **Click `Deploy`** to deploy the Test Runner component, or use `Configure and Deploy` for additional configurations.\n5. After deployment, go to `Execute` and select the environment.\n6. **Click `Run Now`** to trigger the test execution.\n7. Once execution is completed, click on a particular execution to view the test results.\n\n**Frontend Testing**\n\n**Access and Test Frontend Application:**\n1. Access the frontend application via its web URL.\n2. Perform manual testing by interacting with the application (e.g., adding items, checking user-specific data)." | D12: 0.90758689 | E12: 0.86083295 | F12: 0.91072106 | G12: 0.92489693 | H12: 0.89166136 | I12: 0.81338046 | J12: 0.91389294 | O12: 0.74563313
A13: 10 | B13: "I'm getting ""procfile not found"" error for my python service. How do I resolve this?" | C13: "The error you're encountering is because Choreo requires a `Procfile` in your Python project's root directory. A `Procfile` is a configuration file used to declare the commands that are run by your application's containers. \n\nFor a Python project, your `Procfile` might look something like this:\n```\nweb: <command to start your application>\n``` \nFor example, if you're using Flask, your `Procfile` should look like this:\n```\nweb: flask run --host=0.0.0.0\n```\n\nPlease ensure that you have a `Procfile` in your project root directory and that it contains the appropriate command to start your application. You can refer more on this from the [Choreo documentation](https://wso2.com/choreo/docs/develop-components/deploy-an-application-with-buildpacks/#develop-a-component)." | D13: 0.9586671 | E13: 0.89929339 | F13: 0.84650241 | G13: 0.92633829 | H13: 0.93033781 | I13: 0.91332289 | J13: 0.93427821 | O13: 0.93633783
A14: 11 | B14: I'm getting .choreo/endpoints.yaml not found error. How do I resolve this? | C14: "The error message you're seeing, '.choreo/endpoints.yaml not found', indicates that the `endpoints.yaml` file is missing from your project's root directory in the `.choreo` folder. This file is required to define the endpoints for your service component. \n\nTo resolve this error, you need to create an `endpoints.yaml` file in the `.choreo` directory at the build context path and commit it to the source repository. The `endpoints.yaml` file should contain details about the endpoints that your service component will expose. Here is a sample `endpoints.yaml` file:\n\n```yaml\nversion: 0.1\nendpoints:\n- name: Your Service\n port: 9090\n type: REST\n networkVisibility: Project\n context: /your_service\n schemaFilePath: your_service_openapi.yaml\n```\n\nIn this file:\n\n- `name` is a unique name for the endpoint, which Choreo will use to generate the managed API.\n- `port` is the numeric port value that gets exposed via this endpoint.\n- `type` is the type of traffic this endpoint is accepting, such as `REST`, `GraphQL`, `gRPC`, `UDP`or `TCP`.\n- `networkVisibility` is the network level visibility of this endpoint, which defaults to `Public` if not specified. Accepted values are `Project`, `Organization`, or `Public`.\n- `context` is the context (base path) of the API that Choreo exposes via this endpoint. \n- `schemaFilePath` is the swagger definition file path. This field should be a relative path to the project path.\n\nPlease make sure to replace 'Your Service' and '/your_service' with the actual name and context of your service, and 'your_service_openapi.yaml' with the actual OpenAPI schema file.\n\nFor more detailed information about the `endpoints.yaml` file and its structure, you can refer to the following documentation" | D14: 0.95151605 | E14: 0.89999878 | F14: 0.91848379 | G14: 0.91840725 | H14: 0.90374665 | I14: 0.89699052 | J14: 0.87192673 | O14: 0.92724477
A15: 12 | B15: Tell me how I can configure a readiness probe? | C15: "To configure a readiness probe in Choreo, follow these steps:\n\n1. In the **Component Listing** pane, click on the component for which you want to configure readiness probes.\n2. In the left navigation menu, click **DevOps** and then click **Health Checks**.\n3. On the **Health Checks** page, click **+ Create**.\n4. Configure the readiness probe depending on your requirement.\n5. Click **Save**. \n\nYou can update or remove a probe at any time. After setting up the probe, you can ensure that the container works as expected by clicking **Runtime** under **DevOps** in the left navigation menu. On the **Runtime** page, check the details to confirm that the container works as expected. If the container does not start, check the **events and conditions** to see if any of the probes are causing the container to fail.\n\nReadiness probes run periodically throughout the lifecycle of a container. Unlike liveness probes, these probes do not restart the container if the probe fails. Instead, they stop the container from receiving network traffic. Be mindful when you configure readiness probes on a single-running replica. If the readiness probe fails, your application stops receiving traffic because there is only one active replica. The application may not recover unless the liveness probe fails and restarts the container.\n\nYou can configure the following probe types for readiness probes:\n\n- HTTP `GET` request: This probe sends an HTTP `GET` request to a specified port and path on the container. A response status code in the range of 200-399 indicates that the request is a success. Depending on your requirement, you can configure additional HTTP headers. The recommended approach is to create a `/healthz` or `/health` endpoint in your service for this purpose.\n- TCP connection probe: This probe attempts to open a socket to the container on the specified port. If it cannot establish a TCP connection, it becomes a failure.\n- Execute a command: This probe executes a given script inside the container. A non-zero return from the command is considered a failure. For example, `[\""cat\"", \""/tmp/healthy\""]` is considered healthy if the file `/tmp/healthy` is present. If not, it becomes a failure (non-zero exit code). In such scenarios, the application is responsible for writing and maintaining this file in the specified location.\n\nFor more details, please refer to the [Set Up Health Checks] documentation." | D15: 0.9748025 | E15: 0.92696591 | F15: 0.93796804 | G15: 0.9502545 | H15: 0.92658348 | I15: 0.95761543 | J15: 0.96264656 | O15: 0.72248621
... A45: 42 | B45: My service gets overloaded with requests how to fix this? | C45: "Implementing rate limiting on APIs in Choreo involves the following steps: Access your component from the Component Listing pane. Navigate to the Deploy section in the left menu. In the required environment card, click the view icon for the endpoint you want to apply rate limiting to. In the Endpoint Details pane, click the settings icon. Expand the Rate Limiting section under Manage. Select a Rate Limiting Level and click Apply. Choreo offers two rate-limiting levels: API-level Rate Limiting: Applies the allocated request count for the specified time unit to all operations in the API. Operation-level Rate Limiting: Allows configuring different rate-limiting values for each operation. When rate limiting is enabled, Choreo provides four response headers: x-ratelimit-limit: Shows the request count allocated for the specified time unit. x-ratelimit-reset: Indicates the time remaining to start the next rate-limiting time unit. x-ratelimit-remaining: Shows the remaining request count for the specified time unit. x-ratelimit-enforced: Appears after exceeding the allocated request count. For API Proxy components, the process differs slightly. After step 2, click the settings icon next to API Configuration and proceed directly to selecting the Rate Limiting Level." | D45: 0.81960126 | E45: 0.83885681 | F45: 0.88697387 | G45: 0.87060135 | H45: 0.85557087 | I45: 0.88122513 | J45: 0.78653341 | O45: 0.85013487

Sheet Graphs
A1: Copilot vs Fine Tuned - Semantic Similarity
A35: 3B Instruct vs Fine Tuned - Semantic Similarity
A70: 7B Instruct vs Fine Tuned - Semantic Similarity
A105: 3B vs 7B Instruct- Semantic Similarity
A140: 3B vs 7B Fine Tuned - Semantic Similarity

Sheet Individual Answers
E1: Qwen2.5 | K1: Qwen3 | O1: GPT-4o-mini (no RAG)
E2: 3B | H2: 7B | K2: 4B | M2: 8B
A3: Question # | B3: Question | C3: Ground truth | D3: Copilot (GPT-4o-mini + RAG) | E3: Instruct | F3: Fine Tuned | G3: FT Simple Prompt | H3: Instruct | I3: Fine Tuned | J3: FT Simple Prompt | K3: Instruct | L3: Fine Tuned | M3: Instruct | N3: Fine Tuned
A4: 1 | B4: How to deploy a webapp? | C4: "To deploy a web application in Choreo, follow the steps below:\n\n1. **Create a project**: On the organization home page, click **+ Create Project**. Enter a display name, unique name, and description for the project. Click **Create**. This creates the project and opens the project home page. \n\n2. **Create a Web Application component**: On the project home page, click **Web Application** under **Create a Single Component**. Enter a unique name and a description for the web application. \n\n3. **Connect to GitHub**: Go to the **GitHub** tab and click **Authorize with GitHub**. If you have not already connected your GitHub repository to Choreo, enter your GitHub credentials and select the repository. You can also paste the repository URL in the **Provide Repository URL** field to connect to it without requiring authorization. \n\n4. **Enter the required information**: Enter the required information such as your GitHub account in the **Organization** field, repository name in the **Repository** field, and the branch name in the **Branch** field. \n\n5. **Select Buildpack**: Select a build Buildpack (eg: NodeJS, React, Python,PHP, etc.) as the **Buildpack** and provide the necessary details (eg: Project Directory, Language Version, Port, etc.). \n\n6. **Create the component**: Click **Create**. Choreo initializes the component with the sample implementation and opens the **Overview** page of the component.\n\n7. **Build your web application**: In the left navigation menu, click **Build**.In the Builds pane, click **Build**. This opens the Commits pane, where you can see all the commits related to the component. Select the latest commit and click **Build**. This triggers the build process and displays the progress in the **Build Logs pane**.\n\n8. **Deploy the web application**: In the left navigation menu, click **Deploy**. In the **Set Up** card, click **Configure and Deploy**. Click **Next** to move to the **Authentication Settings** pane. Keep the default settings and click **Deploy**. \n\n9. **Verify the deployment**: To verify that you have successfully hosted the web application, click the **Web App URL** in the **Development** card. This takes you to the web application." | D4: "To deploy a web application using Choreo, you need to create a Web Application component and connect it to a Git repository containing your web application's source code. Here’s a structured approach to do this:\n\n### Steps to Deploy a Web Application\n\n1. **Create a Web Application Component**:\n - On the project home page, click on **Web Application** under the **Create a Component** section.\n - Choose to **Authorize with GitHub** to connect Choreo to your GitHub account. If you haven’t connected your GitHub repository yet, you will need to enter your credentials and select the appropriate repository. Alternatively, you can use a public GitHub repository by pasting the repository URL in the provided field.\n\n2. **Enter Repository Details**:\n - Fill in the following information:\n | **Field** | **Value** |\n |------------------------------|-----------------------------|\n | **GitHub Account** | Your account |\n | **GitHub Repository** | Your repository name |\n | **Branch** | main (or your target branch)|\n | **Component Directory** | The directory of your application (if applicable) |\n\n3. **Select Buildpack and Specify Build Options**:\n - Choose the relevant buildpack based on your web application framework (e.g., **React**, **Angular**, or **NodeJS** for server-side applications).\n - Provide the necessary build command, build path, and specify the Node.js version if required:\n | **Field** | **Description** |\n |------------------------------|----------------------------|\n | **Build Command** | Command to build your app (e.g., `npm run build`) |\n | **Build Path** | Output directory (e.g., `build`) |\n | **Node Version** | Specify the Node.js version (e.g., `18`) |\n\n4. **Configure Application Settings**:\n - Enter a unique name and description for your web application component.\n\n5. **Create the Component**:\n - Click **Create**. Choreo will initialize the component with the provided settings and open the **Overview** page of the component.\n\n6. **Build and Deploy**:\n - Once the component is created, Choreo should automatically generate a build pipeline for your web application and deploy it.\n\n### Additional Notes\n- If you are deploying a simple static website, you can use the **Static Websites** buildpack, which doesn't trigger a build process and serves the files directly from the specified path in your repository.\n- If you are using a Dockerfile for a containerized application, connect a repository containing the Dockerfile and follow the appropriate build steps.\n\nFor more detailed instructions, you can refer to the following documents:\n- [Build and Deploy a Single-Page Web Application](https://wso2.com/choreo/docs/develop-components/develop-web-applications/build-and-deploy-a-single-page-web-application/#create-a-web-application)\n- [Deploy Your First Static Web Application](https://wso2.com/choreo/docs/quick-start-guides/deploy-your-first-static-web-application/#step-2-create-a-web-application-component)" | E4: Deploying a web app on the Choreo platform typically involves several steps, but since I don't have direct access to the Choreo environment, I will guide you through the process assuming it's similar to deploying a web application in any environment. If you need more specifics about Choreo, consider looking into the documentation available there. ### Step-by-Step Guide to Deploy a Web App #### 1. Set Up Your Development Environment Make sure your local development environment is ready. You need Node.js and NPM (Node Package Manager) installed. You can install Node.js from [nodejs.org](https://nodejs.org/). Also, make sure you have Git for version control. ```sh # Install Node.js (latest LTS release) # Open https://nodejs.org/en/ ``` #### 2. Create Your Web App You can use a text editor or IDE (Integrated Development Environment) to write your web application code. Let’s assume your web application is a simple Express.js application. Here are the steps to create one: ```js // app.js const express = require('express'); const app = express(); const PORT = process.env.PORT || 3000; app.get('/', (req, res) => { res.send('Welcome to my Web App! '); }); app.listen(PORT, () => { console.log(`App running on port ${PORT}`); }); ``` Install Express.js using npm: ```sh npm install express ``` Initialize a new Node.js project: ```sh npm init -y ``` #### 3. Commit Files Commit your changes to your Git repository: ```sh git init git add . git commit -m "Add my first web application" ``` #### 4. Push to a Version Control System If your organization has a centralized source control system, push the code to the repository: ```sh git push origin master ``` #### 5. Create an API Service (if needed) If your application needs to interact with a backend, you might be setting up an API service too. Create the necessary files, and then you can use Choreo’s API services to set this up. For instance, create an API endpoint like `users`: ```js // user.js const express = require('express'); const app = express(); app.post('/api/users', (req, res) => { const user = req.body; res.send({message: 'User created!', user}); }); app.listen(3001, () => { console.log(`User Service running on port 3001`); }); ``` Again, initialize a Node.js project, commit the changes, push to the repository, and set up your API in Choreo. #### 6. Connect Services and Consumers Using Choreo’s Dashboard and/or its CLI, connect your web app and API services. Ensure they are communicating securely with each other (using OAuth, JWT tokens, etc.). #### 7. Deploy to Choreo (Optional Step) To deploy your app to Choreo, you may want to create a choreo-app.json file if you’re using a custom solution or utilize their built-in support for automatic deployments: ```json { "deploy": { "type": "auto" } } ``` In Choreo Dashboard, go to **Projects**, create or select an existing project, and follow their deployment instructions or connect to your service. Please note, this example is a generic guide. Detailed instructions depend on the specific needs and configuration required by your web app and Choreo service integration. For further detailed steps and security configurations, please consult the Choreo documentation: . | F4: To deploy a web application on the Choreo platform, follow these steps: ### Prerequisites 1. Ensure you have the required permissions for your organization. Typically, the minimum required permissions are: **Organization Read**, **Project Read**, and **Project Write**. ### Steps to Deploy a Web Application in Choreo 1. **Create a Web Application Component**: If you already have an application connected to your Git repository, proceed to the next step. Otherwise, connect your GitHub repository to Choreo by following the [Choreo Connect GitHub Repositories](https://wso2.com/choreo/docs/develop-components/develop-web-applications/connect-github-repos-choreo/#connect-github-repos-to-choreo) guide. 2. In the left navigation menu of the Choreo Console, click **Deploy**. 3. Select your component from the list of components to view the **Deploy** page. 4. In the **Set Up** card on the **Deploy** page, ensure you have filled in the mandatory fields such as a display name, name, version, project, label, description, and build pack. 5. Click on **Deploy** to start the deployment process. The build configuration will appear once the deployment completes successfully. ### Additional Notes - Choreo automatically applies best practices like microservices architecture and follows a modular design principle. - After the initial deployment, you can update the source code, apply new configurations, or rebuild your container image when changes are made in the source code repositories linked to the respective components. For more detailed guidance, you can refer to the official documentation here: [Deploy Your First Web Application](https://wso2.com/choreo/docs/develop-components/deploy-your-first-web-application/#step-3-deploy-the-web-application). | G4: To deploy a web application in Choreo, follow these steps: 1. **Deploy an Application**: - In the Choreo Console left navigation menu, click on **Deploy**. - Select **Web Application** as the buildpack. - Enter your details for deployment, including the name and description. - Click **Configure & Deploy**. The readiness and liveness checks will be automatically configured based on the file type you selected (for example, it will check for a `index.html` file for Node.js applications). - Provide appropriate configurations depending on your application type and save them. 2. **Configure Endpoint Mapping**: - Optionally, configure an endpoint mapping if you want to customize the domain name for accessing your app. If not needed, proceed to the next step. 3. **Promote to Production**: - Click the **Production** card on the Deployment page. - Confirm that the environment label in your Docker image is set to production before proceeding. - Click **Promote** to finalize the promotion. After deploying, your web application will be accessible at its publicly routable URL. If you are using a custom domain, ensure the container name matches your CNAME alias. ### Additional Notes: - You can connect a database when promoting your web application if you have a service connected via buildpack-based microservices. - Be aware of Choreo's logging constraints; logs from your application may not be available after two days and API gateway logs from the past seven days are deleted daily. For further details and specific instructions related to configuring endpoints and promotions, you can refer to the following documentation links: - [Deploy a Single-Page Web Application](https://wso2.com/choreo/docs/develop-components/deploy-a-single-page-web-application/#step-1-deploy-the-web-application) - [Configure Endpoints](https://wso2.com/choreo/docs/develop-components/configure-endpoints/) - [Promote Your Web Application](https://wso2.com/choreo/docs/develop-components/deploy-an-application/) | H4: Deploying a web application on Choreo typically involves integrating it as a service or API within the Choreo environment. However, please note that Choreo primarily focuses on API integration, webhooks, and service management rather than hosting full web applications. If you want to host and manage a web application alongside your APIs in Choreo, you might need to use additional resources or configure your web app to be triggered by events managed within Choreo. Here's how you can deploy and manage a web app or service in Choreo: ### 1. Create a New Web App Service - **Log in to Choreo**: - Open your browser and navigate to the Choreo console URL. - Log in with your credentials. - **Create a New Service**: - In the left sidebar, click on `Services`. - Click on `Add` and select `Web App`. - **Configure Your Service**: - Fill in the required details such as `Name`, `Description`, and `Endpoint URL` (URL of your web app). - Specify the authentication method if needed (e.g., Basic Auth, OAuth). - Configure any necessary settings such as SSL, CORS, and others. ### 2. Integrate with APIs/Webhooks (Optional) - **Create an API**: - Navigate to the `APIs` section. - Click on `Create API` and fill in the required details. - Configure the API endpoints to interact with your web app. - **Integrate with Webhooks**: - Navigate to the `Webhooks` section. - Create a new webhook to trigger events (like HTTP requests) when specific conditions are met, which can then interact with your web app via its endpoint. ### 3. Manage Access Control (Authentication) - **Secure Access**: - Set up authentication and authorization for both the web app and any integrated APIs or webhooks. - You can use various authentication methods supported by Choreo, such as OAuth 2.0, Basic Auth, etc. ### 4. Test and Deploy - **Test the Web App Service**: - Use the `Tests` tab in the service details page to simulate interactions with your web app. - Ensure that the endpoints and interactions are working as expected. - **Deploy**: - Once everything is tested and configured, your web app is considered deployed in the context of Choreo. It can now be accessed and interacted with through the defined endpoints. ### Additional Considerations - **Monitoring and Observability**: - Utilize the logging and monitoring features in Choreo to track the performance and health of your web app interactions. - **Scaling and Performance**: - Configure scaling policies and performance settings if necessary to handle traffic. For more detailed steps and options, please refer to the official Choreo documentation: - [Choreo Services Documentation](https://wso2.com/library/docs/developer/products/choreo/services/) - [Choreo Webhooks Documentation](https://wso2.com/library/docs/developer/products/choreo/webhooks/) - [Choreo API Management Documentation](https://wso2.com/library/docs/developer/products/choreo/api-management/) If you need further assistance with specific configurations or advanced setups, feel free to ask! | I4: To deploy a web application using Choreo, you can follow these steps: ### Step 1: Create a New Project 1. In the Choreo Console, click on **Create**. 2. Choose the **Web Application** card. 3. Select your preferred programming language (such as Go, Java, Node.js, Python, etc.). 4. Provide a name, description, and other project details to complete the creation of your web application project. ### Step 2: Build the Web Application - Choreo automatically builds the source code you provide via a Dockerfile. It follows best practices for secure container building and provides enhanced security features for container creation. - Ensure your web application can be deployed to a specified URL, which will be part of the configuration required during deployment. ### Step 3: Deploy the Web Application - To deploy your web application, go to the **Deploy** section in the Choreo Console. - The deployment process may take some time. You will need to provide configurations for the application, such as domain and port. - After the deployment, verify the URL of your web application to ensure it's accessible. ### Additional Information - If your web application is in an HTTP service, you can invoke it directly through the URL. - For more detailed instructions, you can refer to the documentation on deploying and managing a web application: [Deploy and Manage a Web Application](https://wso2.com/choreo/docs/develop-components/deploy-and-manage-a-web-application). By following these steps, you should be able to successfully deploy your web application using Choreo. | J4: To deploy a web application in Choreo, follow these steps: 1. **Create a Web Application**: You start by creating a web application component. This involves selecting the type of web application you want to develop and configuring it within the Choreo console. For more details, refer to the documentation on creating a web application: [Develop a Web Application](https://wso2.com/choreo/docs/develop-components/develop-web-applications/). 2. **Build and Deploy the Web Application**: - Once your web application is created, navigate to the left menu and click on **Deploy**. - Under the **Build Area** section, click on **Build** to compile your application. - After a successful build, go to the **Deployment Area** section and click **Deploy**. This action will initiate the deployment of your application into the development environment. 3. **View Your Application**: After a successful deployment, you can access your application via the URL provided during the deployment process. 4. **(Optional) Promote the Web Application**: - If you wish to move your application to production, you can promote it. Click on **Promote** under the **Deployment Area** section, then select **Confirm & Promote** when prompted. - Review the configurations and click **Execute** to finalize the promotion to production. For further details, you can refer to the complete documentation on deploying a web application here: [Deploy a Web Application](https://wso2.com/choreo/docs/tutorials/develop-a-single-page-web-application/#step-5-deploy-and-test-the-web-application). | O4: To deploy a web application in Choreo, follow these steps:\n\n1. **Log in to Choreo**:\n - Go to the Choreo dashboard and log in with your credentials.\n\n2. **Create a New Web Application**:\n - Click on the **"Create"** button.\n - Select **"Web Application"** from the options.\n\n3. **Configure Your Web Application**:\n - Provide a name and description for your web application.\n - Choose the appropriate runtime environment (e.g., Node.js, Java, etc.).\n - Set up any necessary configurations, such as environment variables.\n\n4. **Develop Your Application**:\n - Use the integrated code editor to write your application code.\n - You can also upload files or connect to a version control system (like Git) to pull your code.\n\n5. **Set Up Dependencies**:\n - If your application requires external libraries or dependencies, specify them in the configuration settings.\n\n6. **Test Your Application**:\n - Use the built-in testing tools to ensure your application is functioning as expected.\n\n7. **Deploy the Application**:\n - Once you are satisfied with your application, click on the **"Deploy"** button.\n - Choose the deployment environment (e.g., development, production).\n\n8. **Monitor the Deployment**:\n - After deployment, you can monitor the application’s performance and logs through the Choreo dashboard.\n\n9. **Access Your Web Application**:\n - Once deployed, you will receive a URL to access your web application.\n\nFor more detailed instructions and specific configurations, refer to the official Choreo documentation on [Deploying Web Applications](https://choreo.dev/docs/deploying-web-apps).',
A5: 2 | B5: "How to resolve ""Module not found error"" during the deployment of a Python project?" | C5: "To resolve a **Module not found""** error during the deployment of a Python project in Choreo:\n\n1. **Verify Dependencies:**\n - Ensure all required Python modules are in `requirements.txt`\n - Example `requirements.txt`:\n ```plaintext\n flask\n requests\n numpy\n ```\n\n2. **Check File Paths:**\n - Verify that the modules and packages being imported in your Python code have the correct file paths\n\n3. **Rebuild the Component:**\n - Trigger a rebuild after updating `requirements.txt` or file paths. This will ensure that any changes made to the dependencies are included in the new build.\n\n4. **Inspect Logs:**\n - . If the error persists check build logs in Choreo Console UI for detailed error messages. The logs can provide more context on which module is not found and why. \n\n5. **Environment Configuration:**\n - Ensure correct setup of environment variables in Choreo. Sometimes environment variables might be needed for certain modules to work correctly.you can follow these steps:\n\n**Steps to Implement Custom Authentication:**\n\n1. **Add the Connection Configuration:**\n```window.configs = {\napiUrl: '<SERVICE_URL>'" | D5: "To resolve a 'Module not found error' during the deployment of a Python project in Choreo, you can follow these steps:\n\n1. **Check Dependencies**: Ensure that all required modules and dependencies are correctly listed in your project's configuration files, such as `requirements.txt`. If a module is missing from this list, it will not be installed during the deployment process.\n\n2. **Verify Project Structure**: Make sure that your project structure aligns with what is expected in Choreo. The Python files should be in the correct directory, and the main entry point should be properly defined.\n\n3. **Build the Project**: After confirming the dependencies and project structure, you need to rebuild your project. \n - On the project home page, navigate to the component you are deploying.\n - In the left navigation menu, click **Build**, then select **Build Latest**. This will initiate the build process.\n\n4. **Monitor Build Logs**: During the build process, monitor the logs for any errors or warnings that may indicate missing modules or other issues. This information can help you identify and fix the problem before deployment.\n\n5. **Deploy the Project**: If the build is successful, proceed with the deployment. Navigate to the **Deploy** section and follow the necessary steps to configure and deploy your project.\n\nIf you continue to face issues, consider checking the Choreo documentation or community forums for additional troubleshooting tips.\n\nFor more detailed guidance, you can refer to the following document: [Deploy Your First Service](https://wso2.com/choreo/docs/quick-start-guides/deploy-your-first-service/#step-3-build-and-deploy)." | E5: It's important to note that "Module not found" errors generally occur when you try to import a module or package that can't be found during the development or deployment process of your Python project. This type of error is more common in development environments than production. Here are steps you can take to troubleshoot this issue during deployment: ### 1. **Check Project Environment** - Ensure your development environment matches the production environment. This includes: - **Python Version**: Verify the Python version used in both environments. - **Virtual Environments**: Confirm if you are using a virtual environment (e.g., `virtualenv` or `conda`) and that it’s activated in your deployment environment. Example command to activate a virtual environment in a terminal: ```sh source /path/to/venv/bin/activate # On Linux/macOS venv\Scripts\activate # On Windows ``` ### 2. **Inspect Package Installation** - **Ensure Installation Paths**: The installation directory needs to be added to the PYTHONPATH or similar system variable depending on your deployment method (e.g., Docker, Kubernetes, etc.). - **Use a Local Interpreter**: Sometimes, specifying a local interpreter can help avoid dependency conflicts. For example, in `requirements.txt`, you might see something like: ```sh python3/dist-packages/my_module/ ``` ### 3. **Dependency Resolution** - Use the appropriate tools to manage your dependencies. Popular options include `pip` for package installations and `setuptools` and `wheel` for building and installing packages from source. - Use `pip freeze > requirements.txt` to create a list of all installed modules. - Or use `pip install -r requirements.txt` to install specified dependencies. ### 4. **Review Import Syntax** - Make sure there are no syntax errors or typos when importing modules. Double-check import statements in your Python files. For instance: ```python import sys import mymodule ``` ### 5. **Environment Variable Issues** - Sometimes, issues may arise because a required environment variable is not set correctly. Check your application’s configuration or Dockerfile/environment file for any missing variables. ### 6. **Debugging Specific Issues** - For specific error messages related to missing imports, consider these debugging steps: - Run the `setup.py` file (if present in your project) with a verbose mode to ensure proper installation of the required packages. - Check for specific import failures by commenting out code chunks until the error is narrowed down. ### 7. **Documentation Review** - If the error persists, refer back to the documentation of your deployment system or tool (e.g., Docker Compose, Kubernetes YAML, Cloud Formation). It may detail how to set up the required environments or dependencies properly. Remember that troubleshooting such issues requires detailed inspection of your project files and the specific build process being used. Always refer to the specific documentation related to your deployment strategy for precise instructions. If you need help with a particular aspect related to Choreo or related integrations, feel free to ask! | F5: The "Module not found error" typically occurs when your application cannot locate or access the necessary libraries or files that it needs to run properly. This issue can occur both at the time of deployment and while running the deployed application. Here are some strategies you can use to resolve this error: ### Steps to Troubleshoot and Resolve Module Not Found Errors During Deployment: 1. **Verify File Paths**: Ensure that all required files (such as configurations, scripts, etc.) are stored in the correct directory. Sometimes, relative paths may cause the module to be inaccessible. Example: If your `main.py` is located in `/my/project/main.py`, make sure that any other files or directories are accessible through the same path. 2. **Check Libraries**: Confirm that all dependencies are included correctly. Missing or incorrectly referenced third-party libraries can cause a `ModuleNotFoundError`. - Make sure your Dockerfile contains commands to install any necessary dependencies listed in your `requirements.txt` (if you're using a Python project). For example: ```bash cp requirements.txt . pip install --upgrade pip pip install -r requirements.txt ``` 3. **Dockerfile Structure**: If you are using a Dockerfile, ensure it follows best practices: - Use an explicit `WORKDIR` to avoid potential confusion with environment variables. - Ensure the command section is clean and separates from the `COPY` section for better readability and maintainability. ```Dockerfile FROM python:3.7 RUN cp requirements.txt . RUN pip install --upgrade pip && pip install -r requirements.txt COPY . /app WORKDIR /app ENTRYPOINT ["python", "main.py"] # Add other commands here if needed ``` 4. **Container Image Build Failure**: If there are issues during container image build, the command will return with a non-zero exit status, leading to a `ModuleNotFoundError`. To troubleshoot: - Clean the cache before building (`docker build -f -t : -ci .`). - Check if there are any permission errors or file corruption during the build process. 5. **CI/CD Process**: Ensure your Continuous Integration and Continuous Deployment processes are configured correctly: - Check if your component has set up a proper build pack. The build pack handles compiling your code, packaging it into a container image, and pushing it to your preferred cloud environment. - Verify that all environment variables are properly defined and assigned to their respective components. 6. **Logging and Monitoring**: Use logging and monitoring tools within your Choreo Console to track any deployment failures and monitor application logs for clues. ### Common Error Messages: - **No module named 'some_module'**: This indicates that `some_module.py` cannot be found. - **Error reading the manifest file**: This may occur if there are missing or incorrectly formatted dependencies. For more detailed troubleshooting, you can refer to the following links in the Choreo documentation: - [Builds & Deployments](https://wso2.com/choreo/docs/choreo-concepts/ci-cd/#build-and-deploy) - [Build a Container Image From Scratch](https://wso2.com/choreo/docs/develop-components/create-container-image-from-scratch/) | G5: To resolve module-related errors when deploying a Python project in Choreo, especially if you encounter a "Module not found" error, consider the following strategies: ### 1. Correct the Module Path When importing modules that are located in non-standard directories (such as inside virtual environments), ensure that you specify the full path to the required module. This prevents the "Module not found" error. For example: ```python from /absolute/path/to/module import MyClass ``` ### 2. Update Your Project Configuration If your module or dependencies are located elsewhere in the file system, be sure to update the `component.yaml` configuration file accordingly. Ensure that all paths are correctly specified. ### 3. Use an External Virtual Environment Deploying projects with an external virtual environment allows for better isolation and easier management of dependencies. This can mitigate issues related to file structure. ### 4. Handle File Warnings During Deployment Choreo will issue warnings if your source code violates best practices while it is being deployed. Pay attention to any errors related to file paths, imports, or configuration, which could indicate issues with how modules are structured or accessed. ### Example Configuration Ensure your `component.yaml` is set up properly: ```yaml image: "your-image" buildPackConfig: {} envMounts: - name: PYTHON_PATHS value: [/path/to/venv, /path/to/lib] buildpacks: {} cpus: 1 cardinality: SINGULAR portBindingMode: EXTERNAL buildLogUrl: ``` This setup helps choreograph how Choreo interacts with your application and ensures all components function correctly. ### 5. Debugging and Log Monitoring In case of persistent module errors, enabling logging and debugging can provide insights into where things go wrong. Monitor logs to identify any misconfigurations that may lead to the "Module not found" error. By following these steps, you should be able to manage and mitigate module-related errors effectively during the deployment of your Python project in Choreo. For more detailed information, refer to the following links: - [Develop Components With Git](https://wso2.com/choreo/docs/develop-components/develop-components-with-git/#create-a-new-component) - [Develop Applications With Docker](https://wso2.com/choreo/docs/develop-components/develop-applications-with-docker/#create-a-new-containerized-component) - [Manage Component Buildpack Configurations](https://wso2.com/choreo/docs/devops-and-ci-cd/manage-component-buildpack-configurations/) | H5: The "Module not found error" during the deployment of a Python project in Choreo typically indicates that the required Python modules (packages) are not installed in the environment where your application is being run. Hereâ€™s how you can resolve this issue: ### Step-by-Step Guide 1. **Identify the Missing Modules** - Check the error message in the Choreo logs or deployment details for the missing module(s). The error message will usually specify the module name that is missing. 2. **Create a Requirements File** - If you don't already have a `requirements.txt` file, you can create one by listing all the dependencies required by your Python project. ```sh pip freeze > requirements.txt ``` 3. **Verify the Environment Configuration** - Ensure that your Python project is configured to use the correct environment and that it has access to the required modules. 4. **Install Missing Modules in the Deployed Environment** - Use the `requirements.txt` file to install all required packages into the environment used by Choreo. This might be done through the Choreo interface or via the CLI. ```sh pip install -r requirements.txt ``` 5. **Deploy Updated Application** - After ensuring all required modules are installed, redeploy your Python project in Choreo. 6. **Check Deployment Configuration** - Ensure that your Choreo deployment settings are correctly set up to include the necessary paths and configurations to find the required Python packages. 7. **Review Choreo Documentation for Specific Requirements** - Refer to the official Choreo documentation for any specific requirements related to deploying Python projects, including environment configuration and package management. ### Example Scenario in Choreo - **Scenario**: Deploying a Python Flask API in Choreo and getting a "Module not found" error for `flask`. 1. **Identify the Issue:** - You get an error like: `ModuleNotFoundError: No module named 'flask'`. 2. **Update `requirements.txt`:** - Create or edit `requirements.txt` to include `flask`: ``` Flask==2.0.1 ``` - Re-run `pip install -r requirements.txt` locally to verify installation. 3. **Deploy the Updated Application:** - Redeploy the Python Flask API in Choreo, making sure the `requirements.txt` is included and referenced correctly. 4. **Verify the Deployment:** - Once deployed, run the application in Choreo to ensure there are no further errors. ### Links to Documentation - **Creating and Using a `requirements.txt` file**: - [Python Packaging User Guide - requirements](https://packaging.python.org/en/latest/guides/distributing-packages-using-setuptools/#requirements) - **Choreo Documentation for Deployment:** - [Official Choreo Documentation - Deploying Integrations](https://docs.choreo.io/docs/deploy-integration) If you encounter persistent issues after following these steps, please provide more details or specific error messages so further assistance can be given. | I5: The "Module not found error" encountered during the deployment of a Python project in Choreo can typically be resolved by ensuring that all required dependencies are correctly specified in your project’s requirements file and that they are included in the buildpack. ### Steps to Resolve "Module Not Found Error": 1. **Specify Dependencies**: Ensure that your `requirements.txt` file includes all the necessary packages needed for your Python application. For example: ```txt fastapi>=0.78.0 pydantic>=1.10.3 uvicorn>=0.20.0 ``` This file should be placed at the root of your source code directory. If it isn’t there, make sure to include it. 2. **Ensure Correct Build Configuration**: When building your component, verify that the necessary buildpack settings for Python are properly configured to include all dependencies. 3. **Check Component Configuration**: If applicable, update the **Component Configurations** to reflect any specific settings related to your deployment. 4. **Redeploy Your Component**: After making these changes, go to the **Deploy** page and click on **Configure & Deploy** to apply the updates. If the issue persists despite these steps, consider checking the logs for more detailed error messages that might provide additional insights into what is missing or incorrect. For further details, you can refer to the following documents: - [Choreo Build and Deployment Architecture](https://wso2.com/choreo/docs/references/choreo-build-and-deployment-architecture/#build-process) - [Build Python Projects](https://wso2.com/choreo/docs/develop-components/build-and-deploy-python-code/) | J5: To resolve the "Module not found error" during the deployment of a Python project in Choreo, you can try the following strategies: ### 1. **Update Pip Cache** Sometimes, the module might not be recognized due to caching issues. You can try to clear the pip cache before installing your dependencies. ```bash pip3 clean --all ``` Then proceed with installing your dependencies as usual: ```bash pip3 install -r requirements.txt ``` This approach helps ensure that the latest packages are fetched and installed correctly. ### 2. **Use a Requirements File** Ensure you have a `requirements.txt` file in your source directory containing all the required libraries for your application. This file should list all dependencies needed for your project. A sample `requirements.txt` file may look like this: ``` flask==2.0.2 requests==2.26.0 ``` Make sure to commit this file along with your code. ### 3. **Buildpack Configuration** If the above methods do not work, you may need to configure the buildpack for your specific project. However, note that this option is available only if your repository contains a supported buildpack for your project. #### Steps to Configure Buildpacks: - **Select Component Area**: Navigate to the area where you want to set the buildpack configuration. - **Choose Buildpack**: In the **Build Configurations** pane, select **Configure with Buildpack** and specify the buildpack that works best for your application. - **Additional Arguments**: You can input additional arguments in the text box, though this is typically used only for experimental purposes or setting environment variables for a buildpack. For more detailed steps, you can refer to the relevant section in the documentation: [Build components with buildpacks](https://wso2.com/choreo/docs/develop-components/bring-your-own-code/#build-components-with-buildpacks). ### Conclusion By following these suggestions, you should be able to address the "Module not found error" and successfully deploy your Python project in Choreo. If you continue to experience issues, please provide more details about the error messages for further assistance. | O5: To resolve a "Module not found error" during the deployment of a Python project in Choreo, follow these steps:\n\n1. **Check Requirements**:\n - Ensure that all required modules are listed in your `requirements.txt` file. This file should include all dependencies your project needs to run.\n\n2. **Verify Installation**:\n - Make sure that the modules are installed in your environment. You can do this by running:\n ```bash\n pip install -r requirements.txt\n ```\n\n3. **Check Python Version**:\n - Ensure that the Python version you are using locally matches the version specified in Choreo. Some modules may not be compatible with different Python versions.\n\n4. **Use Virtual Environments**:\n - If you are using a virtual environment, ensure that it is activated when you are deploying your project. This helps in isolating dependencies.\n\n5. **Deployment Configuration**:\n - Review your deployment configuration in Choreo. Ensure that the correct environment variables and settings are configured.\n\n6. **Logs and Error Messages**:\n - Check the deployment logs for any specific error messages that might indicate which module is missing. This can provide clues on what needs to be fixed.\n\n7. **Re-deploy**:\n - After making the necessary changes, try re-deploying your project to see if the issue is resolved.\n\n8. **Consult Documentation**:\n - If the issue persists, refer to the official Choreo documentation for any specific guidelines related to Python project deployment: [Choreo Documentation](https://choreo.dev/docs).\n\nBy following these steps, you should be able to resolve the "Module not found error" during your Python project deployment in Choreo.',
